Workbook
Name INPC: #REF!
Name MESES: #REF!
Name NoPadres: #REF!
Name Respuesta: #REF!

Sheet Cálculo de Pensión
B6: Asegurada(o): | E6: Fecha de Cálculo: | F6: =TODAY() -> 46043
B7: NSS: | E7: Fecha de Nacimiento: | F7: 25609
B8: Curp: | E8: Edad Actual: | F8: =IFERROR(IF(ISBLANK(F7),"",TRUNC((F6-F7)/365)),"") -> 55
E9: Fecha de baja: | F9: 44333
C11: Fecha Límite de Conservación de Derechos: | D11: =IF(F9="","",(F12*7/4)+F9) -> 45766.25 | E11: Edad de Retiro: | F11: 60
C12: Fecha Límite para inscribirse en Modalidad 40: | D12: =IF(F9="","",F9+1820) -> 46153 | E12: Total de semanas cotizadas: | F12: 819
E13: Semanas por cotizar Mod. 40 | F13: =TRUNC(AmortizaciónPagos!G28) -> 0
E14: Semanas por reintegrar: | F14: 0
E15: Semanas por aclarar: | F15: 0
E16: Total semanas para cálculo: | F16: =SUM(F12:F15) -> 819
E18: Salario promedio últimas 250 semanas: | F18: ='Salario Promedio'!G68 -> 0
E20: Esposa o concubina: | F20: SI
E21: Hijos menores de 16 años o menores de 25 años (Estudiando): | F21: 2
E22: Padres que dependan económicamente del asegurado: | F22: 0
E26: Valor de unidad de medida (UMA): | F26: 103.74
E27: Salario mínimo vigente: | F27: 207.44
E28: Salario en veces unidad de medida: | F28: =F18/F26 -> 0
E34: Salario promedio últimas 250 semanas: | F34: =F18 -> 0
E35: Porcentaje de cuantía básica: | F35: =VLOOKUP(F28,TblPorcentajesLey73!$B$6:$E$28,3) -> 0.8
E36: Cuantía básica por día: | F36: =F34*F35 -> 0
E37: Cuantía básica anual (365 días): | F37: =F36*365 -> 0
E38: CUANTÍA BÁSICA: | F38: =(1.11)*(F36*365) -> 0
E42: Salario promedio últimas 250 semanas: | F42: =F18 -> 0
E43: Porcentaje de cuantía básica: | F43: =VLOOKUP(F28,TblPorcentajesLey73!$B$6:$E$28,4) -> 0.00563
E44: Incremento diario: | F44: =F42*F43 -> 0
E45: Incremento Anual: | F45: =F44*365 -> 0
E46: Incrementos a la cuantía (Después de las primeras 500 semanas): | F46: =TblPorcentajesLey73!O21 -> 6
E47: Importe total de incrementos anuales a la cuantía básica: | F47: =F45*F46*1.11 -> 0
E49: CUANTÍA DE LA PENSIÓN ANUAL POR VEJEZ: | F49: =F38+F47 -> 0
E53: Edad del trabajador al solicitar la pensión: | F53: =$F$11 -> 60
E54: Porcentaje correspondiente por edad de Cesantía: | F54: =VLOOKUP(F53,TblPorcentajesLey73!$G$6:$H$11,2) -> 0.75
E55: Pensión de Cesantía en Edad Avanzada | F55: =F49*F54 -> 0
E61: Cuantía de la pensión anual: | F61: =$F$55 -> 0
E62: Asignación del: | F62: 0.15
E63: Importe total de asignación por Esposa o Concubina: | F63: =IF(F20="NO",0,F61*F62) -> 0
E67: Cuantía de la pensión anual: | F67: =$F$55 -> 0
E68: Asignación por cada hijo del: | F68: 0.1
E69: Número de hijos menores de edad o estudiantes menores de 25 años: | F69: =F$21 -> 2
E70: Importe total de asignación por hijos dependientes: | F70: =F67*F68*F69 -> 0
E74: Cuantía de la pensión anual: | F74: =$F$55 -> 0
E75: Asignación por cada padre: | F75: 0.1
E76: Número de padres: | F76: =$F$22 -> 0
E77: Importe total de asignación por padres dependientes: | F77: =IF(AND(F20="NO",F21=0),F74*F75*F76,0) -> 0
E81: Cuantía de la pensión anual: | F81: =$F$55 -> 0
E82: Asignación del: | F82: 0.15
E83: Ayuda asistencial por soledad: | F83: =IF(AND($F$20="NO",$F$21=0,$F$22=0),F82*F81,0) -> 0
E85: IMPORTE TOTAL DE LA PENSIÓN DE CESANTÍA EN EDAD AVANZADA: | F85: =F55+F63+F70+F77+F83 -> 0
E87: IMPORTE MENSUAL DE LA PENSIÓN DE CESANTÍA EN EDAD AVANZADA: | F87: =(F57+F65+F72+F79+F85) / 12 -> 0
E89: AGUINALDO | F89: =F55/12 -> 0
E93: Total de pensión mensual antes de impuestos: | F93: =F87 -> 0
E94: Excensión de ISR (15 UMAs): | F94: =F26*15*30.4 -> 47305.44
E95: ISR por pagar: | F95: =TblISR!B9 -> 0
E96: Total de pensión a recibir mensualmente libre de impuestos: | F96: =F93-F95 -> 0
E98: Pensión mensual mínima: | F98: =F27*365/12*1.11 -> 7003.693
E102: Fecha de inicio de pago Modalidad 40:
E103: Fecha de término de pago Modalidad 40:
E104: Inversión total en Modalidad 40: | F104: =AmortizaciónPagos!G25 -> 0
E105: Tiempo de recuperación en meses: | F105: =IFERROR(F104/F96,"")
E106: De su inversión en Modalidad 40 este monto se va al fondo de retiro de su afore: | F106: =AmortizaciónPagos!G26 -> 0

Sheet Salario Promedio
B4: FECHA ALTA | C4: FECHA BAJA | D4: DIAS | E4: SEMANAS | F4: SALARIO DIARIO | G4: S.D. Acumulado
D5: =IF(ISBLANK(B5),0,IF(((C5-B5+1)+I4)>1750,1750-I4,C5-B5+1)) -> 0 | E5: =+D5/7 -> 0 | G5: =D5*F5 -> 0 | H5: =E5 -> 0 | I5: =+D5 -> 0 | J5: =F5*D5 -> 0
D6: =IF(ISBLANK(B6),0,IF(((C6-B6+1)+I5)>1750,1750-I5,C6-B6+1)) -> 0 | E6: =IF((D6/7)+H5>250,250-H5,D6/7) -> 0 | G6: =D6*F6 -> 0 | H6: =E6+H5 -> 0 | I6: =I5+D6 -> 0 | J6: =F6*D6 -> 0
C7: =IF(ISBLANK(B7)," ",B6-1) | D7: =IF(ISBLANK(B7),0,IF(((C7-B7+1)+I6)>1750,1750-I6,C7-B7+1)) -> 0 | E7: =IF((D7/7)+H6>250,250-H6,D7/7) -> 0 | G7: =D7*F7 -> 0 | H7: =E7+H6 -> 0 | I7: =I6+D7 -> 0 | J7: =F7*D7 -> 0
C8: =IF(ISBLANK(B8)," ",B7-1) | D8: =IF(ISBLANK(B8),0,IF(((C8-B8+1)+I7)>1750,1750-I7,C8-B8+1)) -> 0 | E8: =IF((D8/7)+H7>250,250-H7,D8/7) -> 0 | G8: =D8*F8 -> 0 | H8: =E8+H7 -> 0 | I8: =I7+D8 -> 0 | J8: =F8*D8 -> 0
C9: =IF(ISBLANK(B9)," ",B8-1) | D9: =IF(ISBLANK(B9),0,IF(((C9-B9+1)+I8)>1750,1750-I8,C9-B9+1)) -> 0 | E9: =IF((D9/7)+H8>250,250-H8,D9/7) -> 0 | G9: =D9*F9 -> 0 | H9: =E9+H8 -> 0 | I9: =I8+D9 -> 0 | J9: =F9*D9 -> 0
C10: =IF(ISBLANK(B10)," ",B9-1) | D10: =IF(ISBLANK(B10),0,IF(((C10-B10+1)+I9)>1750,1750-I9,C10-B10+1)) -> 0 | E10: =IF((D10/7)+H9>250,250-H9,D10/7) -> 0 | F10: 130 | G10: =D10*F10 -> 0 | H10: =E10+H9 -> 0 | I10: =I9+D10 -> 0 | J10: =F10*D10 -> 0
C11: =IF(ISBLANK(B11)," ",B10-1) | D11: =IF(ISBLANK(B11),0,IF(((C11-B11+1)+I10)>1750,1750-I10,C11-B11+1)) -> 0 | E11: =IF((D11/7)+H10>250,250-H10,D11/7) -> 0 | G11: =D11*F11 -> 0 | H11: =E11+H10 -> 0 | I11: =I10+D11 -> 0 | J11: =F11*D11 -> 0
C12: =IF(ISBLANK(B12)," ",B11-1) | D12: =IF(ISBLANK(B12),0,IF(((C12-B12+1)+I11)>1750,1750-I11,C12-B12+1)) -> 0 | E12: =IF((D12/7)+H11>250,250-H11,D12/7) -> 0 | G12: =D12*F12 -> 0 | H12: =E12+H11 -> 0 | I12: =I11+D12 -> 0 | J12: =F12*D12 -> 0
C13: =IF(ISBLANK(B13)," ",B12-1) | D13: =IF(ISBLANK(B13),0,IF(((C13-B13+1)+I12)>1750,1750-I12,C13-B13+1)) -> 0 | E13: =IF((D13/7)+H12>250,250-H12,D13/7) -> 0 | G13: =D13*F13 -> 0 | H13: =E13+H12 -> 0 | I13: =I12+D13 -> 0 | J13: =F13*D13 -> 0
C14: =IF(ISBLANK(B14)," ",B13-1) | D14: =IF(ISBLANK(B14),0,IF(((C14-B14+1)+I13)>1750,1750-I13,C14-B14+1)) -> 0 | E14: =IF((D14/7)+H13>250,250-H13,D14/7) -> 0 | G14: =D14*F14 -> 0 | H14: =E14+H13 -> 0 | I14: =I13+D14 -> 0 | J14: =F14*D14 -> 0
C15: =IF(ISBLANK(B15)," ",B14-1) | D15: =IF(ISBLANK(B15),0,IF(((C15-B15+1)+I14)>1750,1750-I14,C15-B15+1)) -> 0 | E15: =IF((D15/7)+H14>250,250-H14,D15/7) -> 0 | G15: =D15*F15 -> 0 | H15: =E15+H14 -> 0 | I15: =I14+D15 -> 0 | J15: =F15*D15 -> 0
C16: =IF(ISBLANK(B16)," ",B15-1) | D16: =IF(ISBLANK(B16),0,IF(((C16-B16+1)+I15)>1750,1750-I15,C16-B16+1)) -> 0 | E16: =IF((D16/7)+H15>250,250-H15,D16/7) -> 0 | G16: =D16*F16 -> 0 | H16: =E16+H15 -> 0 | I16: =I15+D16 -> 0 | J16: =F16*D16 -> 0
C17: =IF(ISBLANK(B17)," ",B16-1) | D17: =IF(ISBLANK(B17),0,IF(((C17-B17+1)+I16)>1750,1750-I16,C17-B17+1)) -> 0 | E17: =IF((D17/7)+H16>250,250-H16,D17/7) -> 0 | G17: =D17*F17 -> 0 | H17: =E17+H16 -> 0 | I17: =I16+D17 -> 0 | J17: =F17*D17 -> 0
C18: =IF(ISBLANK(B18)," ",B17-1) | D18: =IF(ISBLANK(B18),0,IF(((C18-B18+1)+I17)>1750,1750-I17,C18-B18+1)) -> 0 | E18: =IF((D18/7)+H17>250,250-H17,D18/7) -> 0 | G18: =D18*F18 -> 0 | H18: =E18+H17 -> 0 | I18: =I17+D18 -> 0 | J18: =F18*D18 -> 0
C19: =IF(ISBLANK(B19)," ",B18-1) | D19: =IF(ISBLANK(B19),0,IF(((C19-B19+1)+I18)>1750,1750-I18,C19-B19+1)) -> 0 | E19: =IF((D19/7)+H18>250,250-H18,D19/7) -> 0 | G19: =D19*F19 -> 0 | H19: =E19+H18 -> 0 | I19: =I18+D19 -> 0 | J19: =F19*D19 -> 0
C20: =IF(ISBLANK(B20)," ",B19-1) | D20: =IF(ISBLANK(B20),0,IF(((C20-B20+1)+I19)>1750,1750-I19,C20-B20+1)) -> 0 | E20: =IF((D20/7)+H19>250,250-H19,D20/7) -> 0 | G20: =D20*F20 -> 0 | H20: =E20+H19 -> 0 | I20: =I19+D20 -> 0 | J20: =F20*D20 -> 0
C21: =IF(ISBLANK(B21)," ",B20-1) | D21: =IF(ISBLANK(B21),0,IF(((C21-B21+1)+I20)>1750,1750-I20,C21-B21+1)) -> 0 | E21: =IF((D21/7)+H20>250,250-H20,D21/7) -> 0 | G21: =D21*F21 -> 0 | H21: =E21+H20 -> 0 | I21: =I20+D21 -> 0 | J21: =F21*D21 -> 0
C22: =IF(ISBLANK(B22)," ",B21-1) | D22: =IF(ISBLANK(B22),0,IF(((C22-B22+1)+I21)>1750,1750-I21,C22-B22+1)) -> 0 | E22: =IF((D22/7)+H21>250,250-H21,D22/7) -> 0 | G22: =D22*F22 -> 0 | H22: =E22+H21 -> 0 | I22: =I21+D22 -> 0 | J22: =F22*D22 -> 0
... C66: =IF(ISBLANK(B66)," ",B65-1) | D66: =IF(ISBLANK(B66),0,IF(((C66-B66+1)+I65)>1750,1750-I65,C66-B66+1)) -> 0 | E66: =IF((D66/7)+H65>250,250-H65,D66/7) -> 0 | G66: =D66*F66 -> 0 | H66: =E66+H65 -> 0 | I66: =I65+D66 -> 0 | J66: =F66*D66 -> 0
D67: =SUM(D5:D66) -> 0 | E67: =SUM(E5:E66) -> 0 | F67: Suma | G67: =SUM(G5:G66) -> 0 | J67: =SUM(J5:J20) -> 0
F68: S. D. Promedio | G68: =IFERROR(G67/D67,0) -> 0 | J68: =IFERROR(J67/D67,0) -> 0

Sheet AmortizaciónPagos
C4: OPCION A
G5: 2018 | L5: 2019 | Q5: 2020 | V5: 2021 | AA5: 2022 | AF5: 2023 | AK5: 2024 | AP5: 2025 | AU5: 2026 | AZ5: 2027 | BE5: 2028 | BJ5: 2029 | BO5: 2030 | BT5: 2031 | BY5: 2032 | CD5: 2033 | CI5: 2034 | CN5: 2035
C6: Costo de Mod. 40 | G6: 0.10075 | L6: 0.10075 | Q6: 0.10075 | V6: 0.10075 | AA6: 0.10075 | AF6: 0.11166 | AK6: 0.12256 | AP6: 0.13347 | AU6: 0.14438 | AZ6: 0.15528 | BE6: 0.16619 | BJ6: 0.17709 | BO6: 0.188 | BT6: 0.188 | BY6: 0.188 | CD6: 0.188 | CI6: 0.188 | CN6: 0.188
C7: Salario Diario 1 | AK7: 0 | AP7: 0 | AU7: 0 | AZ7: 0 | BE7: 0 | BJ7: 0 | BO7: 0 | BT7: 0 | BY7: 0 | CD7: 0 | CI7: 0 | CN7: 0
C8: Salario Diario 2 | G8: 0 | L8: 0 | Q8: 0 | V8: 0 | AA8: 0 | AF8: 0 | AK8: 0 | AP8: 0 | AU8: 0 | BE8: 0 | BJ8: 0 | BO8: 0 | BT8: 0 | BY8: 0 | CD8: 0 | CI8: 0 | CN8: 0
C9: Enero | D9: 31 | E9: 1 | F9: =IF(F$21,1,0) -> 0 | G9: =IF(E9=1,G$6*D9*G$7*F9,G$6*D9*G$8*F9) -> 0 | H9: =IF(E9=1,2%*D9*G$7*F9,2%*D9*G$8*F9) -> 0 | I9: 31 | J9: 1 | K9: =IF(K$21,1,0) -> 0 | L9: =IF(J9=1,L$6*I9*L$7*K9,L$6*I9*L$8*K9) -> 0 | M9: =IF(J9=1,2%*I9*L$7*K9,2%*I9*L$8*K9) -> 0 | N9: 31 | O9: 1 | P9: =IF(P$21,1,0) -> 0 | Q9: =IF(O9=1,Q$6*N9*Q$7*P9,Q$6*N9*Q$8*P9) -> 0 | R9: =IF(O9=1,2%*N9*Q$7*P9,2%*N9*Q$8*P9) -> 0 | S9: 31 | T9: 1 | U9: =IF(U$21,1,0) -> 0 | V9: =IF(T9=1,V$6*S9*V$7*U9,V$6*S9*V$8*U9) -> 0 | W9: =IF(T9=1,2%*S9*V$7*U9,2%*S9*V$8*U9) -> 0 | X9: 31 | Y9: 1 | Z9: =IF(Z$21,1,0) -> 0 | AA9: =IF(Y9=1,AA$6*X9*AA$7*Z9,AA$6*X9*AA$8*Z9) -> 0 | AB9: =IF(Y9=1,2%*X9*AA$7*Z9,2%*X9*AA$8*Z9) -> 0 | AC9: 31 | AD9: 1 | AE9: =IF(AE$21,1,0) -> 0 | AF9: =IF(AD9=1,AF$6*AC9*AF$7*AE9,AF$6*AC9*AF$8*AE9) -> 0 | AG9: =IF(AD9=1,2%*AC9*AF$7*AE9,2%*AC9*AF$8*AE9) -> 0 | AH9: 31 | AI9: 1 | AJ9: =IF(AJ$21,1,0) -> 0 | AK9: =IF(AI9=1,AK$6*AH9*AK$7*AJ9,AK$6*AH9*AK$8*AJ9) -> 0 | AL9: =IF(AI9=1,2%*AH9*AK$7*AJ9,2%*AH9*AK$8*AJ9) -> 0 | AM9: 31 | AN9: 1 | AO9: =IF(AO$21,1,0) -> 0 | AP9: =IF(AN9=1,AP$6*AM9*AP$7*AO9,AP$6*AM9*AP$8*AO9) -> 0 | AQ9: =IF(AN9=1,2%*AM9*AP$7*AO9,2%*AM9*AP$8*AO9) -> 0 | AR9: 31 | AS9: 1 | AT9: =IF(AT$21,1,0) -> 0 | AU9: =IF(AS9=1,AU$6*AR9*AU$7*AT9,AU$6*AR9*AU$8*AT9) -> 0 | AV9: =IF(AS9=1,2%*AR9*AU$7*AT9,2%*AR9*AU$8*AT9) -> 0 | AW9: 31 | AX9: 1 | AY9: =IF(AY$21,1,0) -> 0 | AZ9: =IF(AX9=1,AZ$6*AW9*AZ$7*AY9,AZ$6*AW9*AZ$8*AY9) -> 0 | BA9: =IF(AX9=1,2%*AW9*AZ$7*AY9,2%*AW9*AZ$8*AY9) -> 0 | BB9: 31 | BC9: 1 | BD9: =IF(BD$21,1,0) -> 0 | BE9: =IF(BC9=1,BE$6*BB9*BE$7*BD9,BE$6*BB9*BE$8*BD9) -> 0 | BF9: =IF(BC9=1,2%*BB9*BE$7*BD9,2%*BB9*BE$8*BD9) -> 0 | BG9: 31 | BH9: 1 | BI9: =IF(BI$21,1,0) -> 0 | BJ9: =IF(BH9=1,BJ$6*BG9*BJ$7*BI9,BJ$6*BG9*BJ$8*BI9) -> 0 | BK9: =IF(BH9=1,2%*BG9*BJ$7*BI9,2%*BG9*BJ$8*BI9) -> 0 | BL9: 31 | BM9: 1 | BN9: =IF(BN$21,1,0) -> 0 | BO9: =IF(BM9=1,BO$6*BL9*BO$7*BN9,BO$6*BL9*BO$8*BN9) -> 0 | BP9: =IF(BM9=1,2%*BL9*BO$7*BN9,2%*BL9*BO$8*BN9) -> 0 | BQ9: 31 | BR9: 1 | BS9: =IF(BS$21,1,0) -> 0 | BT9: =IF(BR9=1,BT$6*BQ9*BT$7*BS9,BT$6*BQ9*BT$8*BS9) -> 0 | BU9: =IF(BR9=1,2%*BQ9*BT$7*BS9,2%*BQ9*BT$8*BS9) -> 0 | BV9: 31 | BW9: 1 | BX9: =IF(BX$21,1,0) -> 0 | BY9: =IF(BW9=1,BY$6*BV9*BY$7*BX9,BY$6*BV9*BY$8*BX9) -> 0 | BZ9: =IF(BW9=1,2%*BV9*BY$7*BX9,2%*BV9*BY$8*BX9) -> 0 | CA9: 31 | CB9: 1 | CC9: =IF(CC$21,1,0) -> 0 | CD9: =IF(CB9=1,CD$6*CA9*CD$7*CC9,CD$6*CA9*CD$8*CC9) -> 0 | CE9: =IF(CB9=1,2%*CA9*CD$7*CC9,2%*CA9*CD$8*CC9) -> 0 | CF9: 31 | CG9: 1 | CH9: =IF(CH$21,1,0) -> 0 | CI9: =IF(CG9=1,CI$6*CF9*CI$7*CH9,CI$6*CF9*CI$8*CH9) -> 0 | CJ9: =IF(CG9=1,2%*CF9*CI$7*CH9,2%*CF9*CI$8*CH9) -> 0 | CK9: 31 | CL9: 1 | CM9: =IF(CM$21,1,0) -> 0 | CN9: =IF(CL9=1,CN$6*CK9*CN$7*CM9,CN$6*CK9*CN$8*CM9) -> 0 | CO9: =IF(CL9=1,2%*CK9*CN$7*CM9,2%*CK9*CN$8*CM9) -> 0
C10: Febrero | D10: 28 | E10: 1 | F10: =IF(F$21,1,0) -> 0 | G10: =IF(E10=1,G$6*D10*G$7*F10,G$6*D10*G$8*F10) -> 0 | H10: =IF(E10=1,2%*D10*G$7*F10,2%*D10*G$8*F10) -> 0 | I10: 28 | J10: 1 | K10: =IF(K$21,1,0) -> 0 | L10: =IF(J10=1,L$6*I10*L$7*K10,L$6*I10*L$8*K10) -> 0 | M10: =IF(J10=1,2%*I10*L$7*K10,2%*I10*L$8*K10) -> 0 | N10: 29 | O10: 1 | P10: =IF(P$21,1,0) -> 0 | Q10: =IF(O10=1,Q$6*N10*Q$7*P10,Q$6*N10*Q$8*P10) -> 0 | R10: =IF(O10=1,2%*N10*Q$7*P10,2%*N10*Q$8*P10) -> 0 | S10: 28 | T10: 1 | U10: =IF(U$21,1,0) -> 0 | V10: =IF(T10=1,V$6*S10*V$7*U10,V$6*S10*V$8*U10) -> 0 | W10: =IF(T10=1,2%*S10*V$7*U10,2%*S10*V$8*U10) -> 0 | X10: 28 | Y10: 1 | Z10: =IF(Z$21,1,0) -> 0 | AA10: =IF(Y10=1,AA$6*X10*AA$7*Z10,AA$6*X10*AA$8*Z10) -> 0 | AB10: =IF(Y10=1,2%*X10*AA$7*Z10,2%*X10*AA$8*Z10) -> 0 | AC10: 28 | AD10: 1 | AE10: =IF(AE$21,1,0) -> 0 | AF10: =IF(AD10=1,AF$6*AC10*AF$7*AE10,AF$6*AC10*AF$8*AE10) -> 0 | AG10: =IF(AD10=1,2%*AC10*AF$7*AE10,2%*AC10*AF$8*AE10) -> 0 | AH10: 29 | AI10: 1 | AJ10: =IF(AJ$21,1,0) -> 0 | AK10: =IF(AI10=1,AK$6*AH10*AK$7*AJ10,AK$6*AH10*AK$8*AJ10) -> 0 | AL10: =IF(AI10=1,2%*AH10*AK$7*AJ10,2%*AH10*AK$8*AJ10) -> 0 | AM10: 28 | AN10: 1 | AO10: =IF(AO$21,1,0) -> 0 | AP10: =IF(AN10=1,AP$6*AM10*AP$7*AO10,AP$6*AM10*AP$8*AO10) -> 0 | AQ10: =IF(AN10=1,2%*AM10*AP$7*AO10,2%*AM10*AP$8*AO10) -> 0 | AR10: 28 | AS10: 1 | AT10: =IF(AT$21,1,0) -> 0 | AU10: =IF(AS10=1,AU$6*AR10*AU$7*AT10,AU$6*AR10*AU$8*AT10) -> 0 | AV10: =IF(AS10=1,2%*AR10*AU$7*AT10,2%*AR10*AU$8*AT10) -> 0 | AW10: 28 | AX10: 1 | AY10: =IF(AY$21,1,0) -> 0 | AZ10: =IF(AX10=1,AZ$6*AW10*AZ$7*AY10,AZ$6*AW10*AZ$8*AY10) -> 0 | BA10: =IF(AX10=1,2%*AW10*AZ$7*AY10,2%*AW10*AZ$8*AY10) -> 0 | BB10: 29 | BC10: 1 | BD10: =IF(BD$21,1,0) -> 0 | BE10: =IF(BC10=1,BE$6*BB10*BE$7*BD10,BE$6*BB10*BE$8*BD10) -> 0 | BF10: =IF(BC10=1,2%*BB10*BE$7*BD10,2%*BB10*BE$8*BD10) -> 0 | BG10: 28 | BH10: 1 | BI10: =IF(BI$21,1,0) -> 0 | BJ10: =IF(BH10=1,BJ$6*BG10*BJ$7*BI10,BJ$6*BG10*BJ$8*BI10) -> 0 | BK10: =IF(BH10=1,2%*BG10*BJ$7*BI10,2%*BG10*BJ$8*BI10) -> 0 | BL10: 28 | BM10: 1 | BN10: =IF(BN$21,1,0) -> 0 | BO10: =IF(BM10=1,BO$6*BL10*BO$7*BN10,BO$6*BL10*BO$8*BN10) -> 0 | BP10: =IF(BM10=1,2%*BL10*BO$7*BN10,2%*BL10*BO$8*BN10) -> 0 | BQ10: 28 | BR10: 1 | BS10: =IF(BS$21,1,0) -> 0 | BT10: =IF(BR10=1,BT$6*BQ10*BT$7*BS10,BT$6*BQ10*BT$8*BS10) -> 0 | BU10: =IF(BR10=1,2%*BQ10*BT$7*BS10,2%*BQ10*BT$8*BS10) -> 0 | BV10: 28 | BW10: 1 | BX10: =IF(BX$21,1,0) -> 0 | BY10: =IF(BW10=1,BY$6*BV10*BY$7*BX10,BY$6*BV10*BY$8*BX10) -> 0 | BZ10: =IF(BW10=1,2%*BV10*BY$7*BX10,2%*BV10*BY$8*BX10) -> 0 | CA10: 28 | CB10: 1 | CC10: =IF(CC$21,1,0) -> 0 | CD10: =IF(CB10=1,CD$6*CA10*CD$7*CC10,CD$6*CA10*CD$8*CC10) -> 0 | CE10: =IF(CB10=1,2%*CA10*CD$7*CC10,2%*CA10*CD$8*CC10) -> 0 | CF10: 28 | CG10: 1 | CH10: =IF(CH$21,1,0) -> 0 | CI10: =IF(CG10=1,CI$6*CF10*CI$7*CH10,CI$6*CF10*CI$8*CH10) -> 0 | CJ10: =IF(CG10=1,2%*CF10*CI$7*CH10,2%*CF10*CI$8*CH10) -> 0 | CK10: 28 | CL10: 1 | CM10: =IF(CM$21,1,0) -> 0 | CN10: =IF(CL10=1,CN$6*CK10*CN$7*CM10,CN$6*CK10*CN$8*CM10) -> 0 | CO10: =IF(CL10=1,2%*CK10*CN$7*CM10,2%*CK10*CN$8*CM10) -> 0
C11: Marzo | D11: 31 | E11: 1 | F11: =IF(F$21,1,0) -> 0 | G11: =IF(E11=1,G$6*D11*G$7*F11,G$6*D11*G$8*F11) -> 0 | H11: =IF(E11=1,2%*D11*G$7*F11,2%*D11*G$8*F11) -> 0 | I11: 31 | J11: 1 | K11: =IF(K$21,1,0) -> 0 | L11: =IF(J11=1,L$6*I11*L$7*K11,L$6*I11*L$8*K11) -> 0 | M11: =IF(J11=1,2%*I11*L$7*K11,2%*I11*L$8*K11) -> 0 | N11: 31 | O11: 1 | P11: =IF(P$21,1,0) -> 0 | Q11: =IF(O11=1,Q$6*N11*Q$7*P11,Q$6*N11*Q$8*P11) -> 0 | R11: =IF(O11=1,2%*N11*Q$7*P11,2%*N11*Q$8*P11) -> 0 | S11: 31 | T11: 1 | U11: =IF(U$21,1,0) -> 0 | V11: =IF(T11=1,V$6*S11*V$7*U11,V$6*S11*V$8*U11) -> 0 | W11: =IF(T11=1,2%*S11*V$7*U11,2%*S11*V$8*U11) -> 0 | X11: 31 | Y11: 1 | Z11: =IF(Z$21,1,0) -> 0 | AA11: =IF(Y11=1,AA$6*X11*AA$7*Z11,AA$6*X11*AA$8*Z11) -> 0 | AB11: =IF(Y11=1,2%*X11*AA$7*Z11,2%*X11*AA$8*Z11) -> 0 | AC11: 31 | AD11: 1 | AE11: =IF(AE$21,1,0) -> 0 | AF11: =IF(AD11=1,AF$6*AC11*AF$7*AE11,AF$6*AC11*AF$8*AE11) -> 0 | AG11: =IF(AD11=1,2%*AC11*AF$7*AE11,2%*AC11*AF$8*AE11) -> 0 | AH11: 31 | AI11: 1 | AJ11: =IF(AJ$21,1,0) -> 0 | AK11: =IF(AI11=1,AK$6*AH11*AK$7*AJ11,AK$6*AH11*AK$8*AJ11) -> 0 | AL11: =IF(AI11=1,2%*AH11*AK$7*AJ11,2%*AH11*AK$8*AJ11) -> 0 | AM11: 31 | AN11: 1 | AO11: =IF(AO$21,1,0) -> 0 | AP11: =IF(AN11=1,AP$6*AM11*AP$7*AO11,AP$6*AM11*AP$8*AO11) -> 0 | AQ11: =IF(AN11=1,2%*AM11*AP$7*AO11,2%*AM11*AP$8*AO11) -> 0 | AR11: 31 | AS11: 1 | AT11: =IF(AT$21,1,0) -> 0 | AU11: =IF(AS11=1,AU$6*AR11*AU$7*AT11,AU$6*AR11*AU$8*AT11) -> 0 | AV11: =IF(AS11=1,2%*AR11*AU$7*AT11,2%*AR11*AU$8*AT11) -> 0 | AW11: 31 | AX11: 1 | AY11: =IF(AY$21,1,0) -> 0 | AZ11: =IF(AX11=1,AZ$6*AW11*AZ$7*AY11,AZ$6*AW11*AZ$8*AY11) -> 0 | BA11: =IF(AX11=1,2%*AW11*AZ$7*AY11,2%*AW11*AZ$8*AY11) -> 0 | BB11: 31 | BC11: 1 | BD11: =IF(BD$21,1,0) -> 0 | BE11: =IF(BC11=1,BE$6*BB11*BE$7*BD11,BE$6*BB11*BE$8*BD11) -> 0 | BF11: =IF(BC11=1,2%*BB11*BE$7*BD11,2%*BB11*BE$8*BD11) -> 0 | BG11: 31 | BH11: 1 | BI11: =IF(BI$21,1,0) -> 0 | BJ11: =IF(BH11=1,BJ$6*BG11*BJ$7*BI11,BJ$6*BG11*BJ$8*BI11) -> 0 | BK11: =IF(BH11=1,2%*BG11*BJ$7*BI11,2%*BG11*BJ$8*BI11) -> 0 | BL11: 31 | BM11: 1 | BN11: =IF(BN$21,1,0) -> 0 | BO11: =IF(BM11=1,BO$6*BL11*BO$7*BN11,BO$6*BL11*BO$8*BN11) -> 0 | BP11: =IF(BM11=1,2%*BL11*BO$7*BN11,2%*BL11*BO$8*BN11) -> 0 | BQ11: 31 | BR11: 1 | BS11: =IF(BS$21,1,0) -> 0 | BT11: =IF(BR11=1,BT$6*BQ11*BT$7*BS11,BT$6*BQ11*BT$8*BS11) -> 0 | BU11: =IF(BR11=1,2%*BQ11*BT$7*BS11,2%*BQ11*BT$8*BS11) -> 0 | BV11: 31 | BW11: 1 | BX11: =IF(BX$21,1,0) -> 0 | BY11: =IF(BW11=1,BY$6*BV11*BY$7*BX11,BY$6*BV11*BY$8*BX11) -> 0 | BZ11: =IF(BW11=1,2%*BV11*BY$7*BX11,2%*BV11*BY$8*BX11) -> 0 | CA11: 31 | CB11: 1 | CC11: =IF(CC$21,1,0) -> 0 | CD11: =IF(CB11=1,CD$6*CA11*CD$7*CC11,CD$6*CA11*CD$8*CC11) -> 0 | CE11: =IF(CB11=1,2%*CA11*CD$7*CC11,2%*CA11*CD$8*CC11) -> 0 | CF11: 31 | CG11: 1 | CH11: =IF(CH$21,1,0) -> 0 | CI11: =IF(CG11=1,CI$6*CF11*CI$7*CH11,CI$6*CF11*CI$8*CH11) -> 0 | CJ11: =IF(CG11=1,2%*CF11*CI$7*CH11,2%*CF11*CI$8*CH11) -> 0 | CK11: 31 | CL11: 1 | CM11: =IF(CM$21,1,0) -> 0 | CN11: =IF(CL11=1,CN$6*CK11*CN$7*CM11,CN$6*CK11*CN$8*CM11) -> 0 | CO11: =IF(CL11=1,2%*CK11*CN$7*CM11,2%*CK11*CN$8*CM11) -> 0
C12: Abril | D12: 30 | E12: 1 | F12: =IF(F$21,1,0) -> 0 | G12: =IF(E12=1,G$6*D12*G$7*F12,G$6*D12*G$8*F12) -> 0 | H12: =IF(E12=1,2%*D12*G$7*F12,2%*D12*G$8*F12) -> 0 | I12: 30 | J12: 1 | K12: =IF(K$21,1,0) -> 0 | L12: =IF(J12=1,L$6*I12*L$7*K12,L$6*I12*L$8*K12) -> 0 | M12: =IF(J12=1,2%*I12*L$7*K12,2%*I12*L$8*K12) -> 0 | N12: 30 | O12: 1 | P12: =IF(P$21,1,0) -> 0 | Q12: =IF(O12=1,Q$6*N12*Q$7*P12,Q$6*N12*Q$8*P12) -> 0 | R12: =IF(O12=1,2%*N12*Q$7*P12,2%*N12*Q$8*P12) -> 0 | S12: 30 | T12: 1 | U12: =IF(U$21,1,0) -> 0 | V12: =IF(T12=1,V$6*S12*V$7*U12,V$6*S12*V$8*U12) -> 0 | W12: =IF(T12=1,2%*S12*V$7*U12,2%*S12*V$8*U12) -> 0 | X12: 30 | Y12: 1 | Z12: =IF(Z$21,1,0) -> 0 | AA12: =IF(Y12=1,AA$6*X12*AA$7*Z12,AA$6*X12*AA$8*Z12) -> 0 | AB12: =IF(Y12=1,2%*X12*AA$7*Z12,2%*X12*AA$8*Z12) -> 0 | AC12: 30 | AD12: 1 | AE12: =IF(AE$21,1,0) -> 0 | AF12: =IF(AD12=1,AF$6*AC12*AF$7*AE12,AF$6*AC12*AF$8*AE12) -> 0 | AG12: =IF(AD12=1,2%*AC12*AF$7*AE12,2%*AC12*AF$8*AE12) -> 0 | AH12: 30 | AI12: 1 | AJ12: =IF(AJ$21,1,0) -> 0 | AK12: =IF(AI12=1,AK$6*AH12*AK$7*AJ12,AK$6*AH12*AK$8*AJ12) -> 0 | AL12: =IF(AI12=1,2%*AH12*AK$7*AJ12,2%*AH12*AK$8*AJ12) -> 0 | AM12: 30 | AN12: 1 | AO12: =IF(AO$21,1,0) -> 0 | AP12: =IF(AN12=1,AP$6*AM12*AP$7*AO12,AP$6*AM12*AP$8*AO12) -> 0 | AQ12: =IF(AN12=1,2%*AM12*AP$7*AO12,2%*AM12*AP$8*AO12) -> 0 | AR12: 30 | AS12: 1 | AT12: =IF(AT$21,1,0) -> 0 | AU12: =IF(AS12=1,AU$6*AR12*AU$7*AT12,AU$6*AR12*AU$8*AT12) -> 0 | AV12: =IF(AS12=1,2%*AR12*AU$7*AT12,2%*AR12*AU$8*AT12) -> 0 | AW12: 30 | AX12: 1 | AY12: =IF(AY$21,1,0) -> 0 | AZ12: =IF(AX12=1,AZ$6*AW12*AZ$7*AY12,AZ$6*AW12*AZ$8*AY12) -> 0 | BA12: =IF(AX12=1,2%*AW12*AZ$7*AY12,2%*AW12*AZ$8*AY12) -> 0 | BB12: 30 | BC12: 1 | BD12: =IF(BD$21,1,0) -> 0 | BE12: =IF(BC12=1,BE$6*BB12*BE$7*BD12,BE$6*BB12*BE$8*BD12) -> 0 | BF12: =IF(BC12=1,2%*BB12*BE$7*BD12,2%*BB12*BE$8*BD12) -> 0 | BG12: 30 | BH12: 1 | BI12: =IF(BI$21,1,0) -> 0 | BJ12: =IF(BH12=1,BJ$6*BG12*BJ$7*BI12,BJ$6*BG12*BJ$8*BI12) -> 0 | BK12: =IF(BH12=1,2%*BG12*BJ$7*BI12,2%*BG12*BJ$8*BI12) -> 0 | BL12: 30 | BM12: 1 | BN12: =IF(BN$21,1,0) -> 0 | BO12: =IF(BM12=1,BO$6*BL12*BO$7*BN12,BO$6*BL12*BO$8*BN12) -> 0 | BP12: =IF(BM12=1,2%*BL12*BO$7*BN12,2%*BL12*BO$8*BN12) -> 0 | BQ12: 30 | BR12: 1 | BS12: =IF(BS$21,1,0) -> 0 | BT12: =IF(BR12=1,BT$6*BQ12*BT$7*BS12,BT$6*BQ12*BT$8*BS12) -> 0 | BU12: =IF(BR12=1,2%*BQ12*BT$7*BS12,2%*BQ12*BT$8*BS12) -> 0 | BV12: 30 | BW12: 1 | BX12: =IF(BX$21,1,0) -> 0 | BY12: =IF(BW12=1,BY$6*BV12*BY$7*BX12,BY$6*BV12*BY$8*BX12) -> 0 | BZ12: =IF(BW12=1,2%*BV12*BY$7*BX12,2%*BV12*BY$8*BX12) -> 0 | CA12: 30 | CB12: 1 | CC12: =IF(CC$21,1,0) -> 0 | CD12: =IF(CB12=1,CD$6*CA12*CD$7*CC12,CD$6*CA12*CD$8*CC12) -> 0 | CE12: =IF(CB12=1,2%*CA12*CD$7*CC12,2%*CA12*CD$8*CC12) -> 0 | CF12: 30 | CG12: 1 | CH12: =IF(CH$21,1,0) -> 0 | CI12: =IF(CG12=1,CI$6*CF12*CI$7*CH12,CI$6*CF12*CI$8*CH12) -> 0 | CJ12: =IF(CG12=1,2%*CF12*CI$7*CH12,2%*CF12*CI$8*CH12) -> 0 | CK12: 30 | CL12: 1 | CM12: =IF(CM$21,1,0) -> 0 | CN12: =IF(CL12=1,CN$6*CK12*CN$7*CM12,CN$6*CK12*CN$8*CM12) -> 0 | CO12: =IF(CL12=1,2%*CK12*CN$7*CM12,2%*CK12*CN$8*CM12) -> 0
C13: Mayo | D13: 31 | E13: 1 | F13: =IF(F$21,1,0) -> 0 | G13: =IF(E13=1,G$6*D13*G$7*F13,G$6*D13*G$8*F13) -> 0 | H13: =IF(E13=1,2%*D13*G$7*F13,2%*D13*G$8*F13) -> 0 | I13: 31 | J13: 1 | K13: =IF(K$21,1,0) -> 0 | L13: =IF(J13=1,L$6*I13*L$7*K13,L$6*I13*L$8*K13) -> 0 | M13: =IF(J13=1,2%*I13*L$7*K13,2%*I13*L$8*K13) -> 0 | N13: 31 | O13: 1 | P13: =IF(P$21,1,0) -> 0 | Q13: =IF(O13=1,Q$6*N13*Q$7*P13,Q$6*N13*Q$8*P13) -> 0 | R13: =IF(O13=1,2%*N13*Q$7*P13,2%*N13*Q$8*P13) -> 0 | S13: 31 | T13: 1 | U13: =IF(U$21,1,0) -> 0 | V13: =IF(T13=1,V$6*S13*V$7*U13,V$6*S13*V$8*U13) -> 0 | W13: =IF(T13=1,2%*S13*V$7*U13,2%*S13*V$8*U13) -> 0 | X13: 31 | Y13: 1 | Z13: =IF(Z$21,1,0) -> 0 | AA13: =IF(Y13=1,AA$6*X13*AA$7*Z13,AA$6*X13*AA$8*Z13) -> 0 | AB13: =IF(Y13=1,2%*X13*AA$7*Z13,2%*X13*AA$8*Z13) -> 0 | AC13: 31 | AD13: 1 | AE13: =IF(AE$21,1,0) -> 0 | AF13: =IF(AD13=1,AF$6*AC13*AF$7*AE13,AF$6*AC13*AF$8*AE13) -> 0 | AG13: =IF(AD13=1,2%*AC13*AF$7*AE13,2%*AC13*AF$8*AE13) -> 0 | AH13: 31 | AI13: 1 | AJ13: =IF(AJ$21,1,0) -> 0 | AK13: =IF(AI13=1,AK$6*AH13*AK$7*AJ13,AK$6*AH13*AK$8*AJ13) -> 0 | AL13: =IF(AI13=1,2%*AH13*AK$7*AJ13,2%*AH13*AK$8*AJ13) -> 0 | AM13: 31 | AN13: 1 | AO13: =IF(AO$21,1,0) -> 0 | AP13: =IF(AN13=1,AP$6*AM13*AP$7*AO13,AP$6*AM13*AP$8*AO13) -> 0 | AQ13: =IF(AN13=1,2%*AM13*AP$7*AO13,2%*AM13*AP$8*AO13) -> 0 | AR13: 31 | AS13: 1 | AT13: =IF(AT$21,1,0) -> 0 | AU13: =IF(AS13=1,AU$6*AR13*AU$7*AT13,AU$6*AR13*AU$8*AT13) -> 0 | AV13: =IF(AS13=1,2%*AR13*AU$7*AT13,2%*AR13*AU$8*AT13) -> 0 | AW13: 31 | AX13: 1 | AY13: =IF(AY$21,1,0) -> 0 | AZ13: =IF(AX13=1,AZ$6*AW13*AZ$7*AY13,AZ$6*AW13*AZ$8*AY13) -> 0 | BA13: =IF(AX13=1,2%*AW13*AZ$7*AY13,2%*AW13*AZ$8*AY13) -> 0 | BB13: 31 | BC13: 1 | BD13: =IF(BD$21,1,0) -> 0 | BE13: =IF(BC13=1,BE$6*BB13*BE$7*BD13,BE$6*BB13*BE$8*BD13) -> 0 | BF13: =IF(BC13=1,2%*BB13*BE$7*BD13,2%*BB13*BE$8*BD13) -> 0 | BG13: 31 | BH13: 1 | BI13: =IF(BI$21,1,0) -> 0 | BJ13: =IF(BH13=1,BJ$6*BG13*BJ$7*BI13,BJ$6*BG13*BJ$8*BI13) -> 0 | BK13: =IF(BH13=1,2%*BG13*BJ$7*BI13,2%*BG13*BJ$8*BI13) -> 0 | BL13: 31 | BM13: 1 | BN13: =IF(BN$21,1,0) -> 0 | BO13: =IF(BM13=1,BO$6*BL13*BO$7*BN13,BO$6*BL13*BO$8*BN13) -> 0 | BP13: =IF(BM13=1,2%*BL13*BO$7*BN13,2%*BL13*BO$8*BN13) -> 0 | BQ13: 31 | BR13: 1 | BS13: =IF(BS$21,1,0) -> 0 | BT13: =IF(BR13=1,BT$6*BQ13*BT$7*BS13,BT$6*BQ13*BT$8*BS13) -> 0 | BU13: =IF(BR13=1,2%*BQ13*BT$7*BS13,2%*BQ13*BT$8*BS13) -> 0 | BV13: 31 | BW13: 1 | BX13: =IF(BX$21,1,0) -> 0 | BY13: =IF(BW13=1,BY$6*BV13*BY$7*BX13,BY$6*BV13*BY$8*BX13) -> 0 | BZ13: =IF(BW13=1,2%*BV13*BY$7*BX13,2%*BV13*BY$8*BX13) -> 0 | CA13: 31 | CB13: 1 | CC13: =IF(CC$21,1,0) -> 0 | CD13: =IF(CB13=1,CD$6*CA13*CD$7*CC13,CD$6*CA13*CD$8*CC13) -> 0 | CE13: =IF(CB13=1,2%*CA13*CD$7*CC13,2%*CA13*CD$8*CC13) -> 0 | CF13: 31 | CG13: 1 | CH13: =IF(CH$21,1,0) -> 0 | CI13: =IF(CG13=1,CI$6*CF13*CI$7*CH13,CI$6*CF13*CI$8*CH13) -> 0 | CJ13: =IF(CG13=1,2%*CF13*CI$7*CH13,2%*CF13*CI$8*CH13) -> 0 | CK13: 31 | CL13: 1 | CM13: =IF(CM$21,1,0) -> 0 | CN13: =IF(CL13=1,CN$6*CK13*CN$7*CM13,CN$6*CK13*CN$8*CM13) -> 0 | CO13: =IF(CL13=1,2%*CK13*CN$7*CM13,2%*CK13*CN$8*CM13) -> 0
C14: Junio | D14: 30 | E14: 1 | F14: =IF(F$21,1,0) -> 0 | G14: =IF(E14=1,G$6*D14*G$7*F14,G$6*D14*G$8*F14) -> 0 | H14: =IF(E14=1,2%*D14*G$7*F14,2%*D14*G$8*F14) -> 0 | I14: 30 | J14: 1 | K14: =IF(K$21,1,0) -> 0 | L14: =IF(J14=1,L$6*I14*L$7*K14,L$6*I14*L$8*K14) -> 0 | M14: =IF(J14=1,2%*I14*L$7*K14,2%*I14*L$8*K14) -> 0 | N14: 30 | O14: 1 | P14: =IF(P$21,1,0) -> 0 | Q14: =IF(O14=1,Q$6*N14*Q$7*P14,Q$6*N14*Q$8*P14) -> 0 | R14: =IF(O14=1,2%*N14*Q$7*P14,2%*N14*Q$8*P14) -> 0 | S14: 30 | T14: 1 | U14: =IF(U$21,1,0) -> 0 | V14: =IF(T14=1,V$6*S14*V$7*U14,V$6*S14*V$8*U14) -> 0 | W14: =IF(T14=1,2%*S14*V$7*U14,2%*S14*V$8*U14) -> 0 | X14: 30 | Y14: 1 | Z14: =IF(Z$21,1,0) -> 0 | AA14: =IF(Y14=1,AA$6*X14*AA$7*Z14,AA$6*X14*AA$8*Z14) -> 0 | AB14: =IF(Y14=1,2%*X14*AA$7*Z14,2%*X14*AA$8*Z14) -> 0 | AC14: 30 | AD14: 1 | AE14: =IF(AE$21,1,0) -> 0 | AF14: =IF(AD14=1,AF$6*AC14*AF$7*AE14,AF$6*AC14*AF$8*AE14) -> 0 | AG14: =IF(AD14=1,2%*AC14*AF$7*AE14,2%*AC14*AF$8*AE14) -> 0 | AH14: 30 | AI14: 1 | AJ14: =IF(AJ$21,1,0) -> 0 | AK14: =IF(AI14=1,AK$6*AH14*AK$7*AJ14,AK$6*AH14*AK$8*AJ14) -> 0 | AL14: =IF(AI14=1,2%*AH14*AK$7*AJ14,2%*AH14*AK$8*AJ14) -> 0 | AM14: 30 | AN14: 1 | AO14: =IF(AO$21,1,0) -> 0 | AP14: =IF(AN14=1,AP$6*AM14*AP$7*AO14,AP$6*AM14*AP$8*AO14) -> 0 | AQ14: =IF(AN14=1,2%*AM14*AP$7*AO14,2%*AM14*AP$8*AO14) -> 0 | AR14: 30 | AS14: 1 | AT14: =IF(AT$21,1,0) -> 0 | AU14: =IF(AS14=1,AU$6*AR14*AU$7*AT14,AU$6*AR14*AU$8*AT14) -> 0 | AV14: =IF(AS14=1,2%*AR14*AU$7*AT14,2%*AR14*AU$8*AT14) -> 0 | AW14: 30 | AX14: 1 | AY14: =IF(AY$21,1,0) -> 0 | AZ14: =IF(AX14=1,AZ$6*AW14*AZ$7*AY14,AZ$6*AW14*AZ$8*AY14) -> 0 | BA14: =IF(AX14=1,2%*AW14*AZ$7*AY14,2%*AW14*AZ$8*AY14) -> 0 | BB14: 30 | BC14: 1 | BD14: =IF(BD$21,1,0) -> 0 | BE14: =IF(BC14=1,BE$6*BB14*BE$7*BD14,BE$6*BB14*BE$8*BD14) -> 0 | BF14: =IF(BC14=1,2%*BB14*BE$7*BD14,2%*BB14*BE$8*BD14) -> 0 | BG14: 30 | BH14: 1 | BI14: =IF(BI$21,1,0) -> 0 | BJ14: =IF(BH14=1,BJ$6*BG14*BJ$7*BI14,BJ$6*BG14*BJ$8*BI14) -> 0 | BK14: =IF(BH14=1,2%*BG14*BJ$7*BI14,2%*BG14*BJ$8*BI14) -> 0 | BL14: 30 | BM14: 1 | BN14: =IF(BN$21,1,0) -> 0 | BO14: =IF(BM14=1,BO$6*BL14*BO$7*BN14,BO$6*BL14*BO$8*BN14) -> 0 | BP14: =IF(BM14=1,2%*BL14*BO$7*BN14,2%*BL14*BO$8*BN14) -> 0 | BQ14: 30 | BR14: 1 | BS14: =IF(BS$21,1,0) -> 0 | BT14: =IF(BR14=1,BT$6*BQ14*BT$7*BS14,BT$6*BQ14*BT$8*BS14) -> 0 | BU14: =IF(BR14=1,2%*BQ14*BT$7*BS14,2%*BQ14*BT$8*BS14) -> 0 | BV14: 30 | BW14: 1 | BX14: =IF(BX$21,1,0) -> 0 | BY14: =IF(BW14=1,BY$6*BV14*BY$7*BX14,BY$6*BV14*BY$8*BX14) -> 0 | BZ14: =IF(BW14=1,2%*BV14*BY$7*BX14,2%*BV14*BY$8*BX14) -> 0 | CA14: 30 | CB14: 1 | CC14: =IF(CC$21,1,0) -> 0 | CD14: =IF(CB14=1,CD$6*CA14*CD$7*CC14,CD$6*CA14*CD$8*CC14) -> 0 | CE14: =IF(CB14=1,2%*CA14*CD$7*CC14,2%*CA14*CD$8*CC14) -> 0 | CF14: 30 | CG14: 1 | CH14: =IF(CH$21,1,0) -> 0 | CI14: =IF(CG14=1,CI$6*CF14*CI$7*CH14,CI$6*CF14*CI$8*CH14) -> 0 | CJ14: =IF(CG14=1,2%*CF14*CI$7*CH14,2%*CF14*CI$8*CH14) -> 0 | CK14: 30 | CL14: 1 | CM14: =IF(CM$21,1,0) -> 0 | CN14: =IF(CL14=1,CN$6*CK14*CN$7*CM14,CN$6*CK14*CN$8*CM14) -> 0 | CO14: =IF(CL14=1,2%*CK14*CN$7*CM14,2%*CK14*CN$8*CM14) -> 0
C15: Julio | D15: 31 | E15: 1 | F15: =IF(F$21,1,0) -> 0 | G15: =IF(E15=1,G$6*D15*G$7*F15,G$6*D15*G$8*F15) -> 0 | H15: =IF(E15=1,2%*D15*G$7*F15,2%*D15*G$8*F15) -> 0 | I15: 31 | J15: 1 | K15: =IF(K$21,1,0) -> 0 | L15: =IF(J15=1,L$6*I15*L$7*K15,L$6*I15*L$8*K15) -> 0 | M15: =IF(J15=1,2%*I15*L$7*K15,2%*I15*L$8*K15) -> 0 | N15: 31 | O15: 1 | P15: =IF(P$21,1,0) -> 0 | Q15: =IF(O15=1,Q$6*N15*Q$7*P15,Q$6*N15*Q$8*P15) -> 0 | R15: =IF(O15=1,2%*N15*Q$7*P15,2%*N15*Q$8*P15) -> 0 | S15: 31 | T15: 1 | U15: =IF(U$21,1,0) -> 0 | V15: =IF(T15=1,V$6*S15*V$7*U15,V$6*S15*V$8*U15) -> 0 | W15: =IF(T15=1,2%*S15*V$7*U15,2%*S15*V$8*U15) -> 0 | X15: 31 | Y15: 1 | Z15: =IF(Z$21,1,0) -> 0 | AA15: =IF(Y15=1,AA$6*X15*AA$7*Z15,AA$6*X15*AA$8*Z15) -> 0 | AB15: =IF(Y15=1,2%*X15*AA$7*Z15,2%*X15*AA$8*Z15) -> 0 | AC15: 31 | AD15: 1 | AE15: =IF(AE$21,1,0) -> 0 | AF15: =IF(AD15=1,AF$6*AC15*AF$7*AE15,AF$6*AC15*AF$8*AE15) -> 0 | AG15: =IF(AD15=1,2%*AC15*AF$7*AE15,2%*AC15*AF$8*AE15) -> 0 | AH15: 31 | AI15: 1 | AJ15: =IF(AJ$21,1,0) -> 0 | AK15: =IF(AI15=1,AK$6*AH15*AK$7*AJ15,AK$6*AH15*AK$8*AJ15) -> 0 | AL15: =IF(AI15=1,2%*AH15*AK$7*AJ15,2%*AH15*AK$8*AJ15) -> 0 | AM15: 31 | AN15: 1 | AO15: =IF(AO$21,1,0) -> 0 | AP15: =IF(AN15=1,AP$6*AM15*AP$7*AO15,AP$6*AM15*AP$8*AO15) -> 0 | AQ15: =IF(AN15=1,2%*AM15*AP$7*AO15,2%*AM15*AP$8*AO15) -> 0 | AR15: 31 | AS15: 1 | AT15: =IF(AT$21,1,0) -> 0 | AU15: =IF(AS15=1,AU$6*AR15*AU$7*AT15,AU$6*AR15*AU$8*AT15) -> 0 | AV15: =IF(AS15=1,2%*AR15*AU$7*AT15,2%*AR15*AU$8*AT15) -> 0 | AW15: 31 | AX15: 1 | AY15: =IF(AY$21,1,0) -> 0 | AZ15: =IF(AX15=1,AZ$6*AW15*AZ$7*AY15,AZ$6*AW15*AZ$8*AY15) -> 0 | BA15: =IF(AX15=1,2%*AW15*AZ$7*AY15,2%*AW15*AZ$8*AY15) -> 0 | BB15: 31 | BC15: 1 | BD15: =IF(BD$21,1,0) -> 0 | BE15: =IF(BC15=1,BE$6*BB15*BE$7*BD15,BE$6*BB15*BE$8*BD15) -> 0 | BF15: =IF(BC15=1,2%*BB15*BE$7*BD15,2%*BB15*BE$8*BD15) -> 0 | BG15: 31 | BH15: 1 | BI15: =IF(BI$21,1,0) -> 0 | BJ15: =IF(BH15=1,BJ$6*BG15*BJ$7*BI15,BJ$6*BG15*BJ$8*BI15) -> 0 | BK15: =IF(BH15=1,2%*BG15*BJ$7*BI15,2%*BG15*BJ$8*BI15) -> 0 | BL15: 31 | BM15: 1 | BN15: =IF(BN$21,1,0) -> 0 | BO15: =IF(BM15=1,BO$6*BL15*BO$7*BN15,BO$6*BL15*BO$8*BN15) -> 0 | BP15: =IF(BM15=1,2%*BL15*BO$7*BN15,2%*BL15*BO$8*BN15) -> 0 | BQ15: 31 | BR15: 1 | BS15: =IF(BS$21,1,0) -> 0 | BT15: =IF(BR15=1,BT$6*BQ15*BT$7*BS15,BT$6*BQ15*BT$8*BS15) -> 0 | BU15: =IF(BR15=1,2%*BQ15*BT$7*BS15,2%*BQ15*BT$8*BS15) -> 0 | BV15: 31 | BW15: 1 | BX15: =IF(BX$21,1,0) -> 0 | BY15: =IF(BW15=1,BY$6*BV15*BY$7*BX15,BY$6*BV15*BY$8*BX15) -> 0 | BZ15: =IF(BW15=1,2%*BV15*BY$7*BX15,2%*BV15*BY$8*BX15) -> 0 | CA15: 31 | CB15: 1 | CC15: =IF(CC$21,1,0) -> 0 | CD15: =IF(CB15=1,CD$6*CA15*CD$7*CC15,CD$6*CA15*CD$8*CC15) -> 0 | CE15: =IF(CB15=1,2%*CA15*CD$7*CC15,2%*CA15*CD$8*CC15) -> 0 | CF15: 31 | CG15: 1 | CH15: =IF(CH$21,1,0) -> 0 | CI15: =IF(CG15=1,CI$6*CF15*CI$7*CH15,CI$6*CF15*CI$8*CH15) -> 0 | CJ15: =IF(CG15=1,2%*CF15*CI$7*CH15,2%*CF15*CI$8*CH15) -> 0 | CK15: 31 | CL15: 1 | CM15: =IF(CM$21,1,0) -> 0 | CN15: =IF(CL15=1,CN$6*CK15*CN$7*CM15,CN$6*CK15*CN$8*CM15) -> 0 | CO15: =IF(CL15=1,2%*CK15*CN$7*CM15,2%*CK15*CN$8*CM15) -> 0
C16: Agosto | D16: 22 | E16: 1 | F16: =IF(F$21,1,0) -> 0 | G16: =IF(E16=1,G$6*D16*G$7*F16,G$6*D16*G$8*F16) -> 0 | H16: =IF(E16=1,2%*D16*G$7*F16,2%*D16*G$8*F16) -> 0 | I16: 31 | J16: 1 | K16: =IF(K$21,1,0) -> 0 | L16: =IF(J16=1,L$6*I16*L$7*K16,L$6*I16*L$8*K16) -> 0 | M16: =IF(J16=1,2%*I16*L$7*K16,2%*I16*L$8*K16) -> 0 | N16: 31 | O16: 1 | P16: =IF(P$21,1,0) -> 0 | Q16: =IF(O16=1,Q$6*N16*Q$7*P16,Q$6*N16*Q$8*P16) -> 0 | R16: =IF(O16=1,2%*N16*Q$7*P16,2%*N16*Q$8*P16) -> 0 | S16: 31 | T16: 1 | U16: =IF(U$21,1,0) -> 0 | V16: =IF(T16=1,V$6*S16*V$7*U16,V$6*S16*V$8*U16) -> 0 | W16: =IF(T16=1,2%*S16*V$7*U16,2%*S16*V$8*U16) -> 0 | X16: 31 | Y16: 1 | Z16: =IF(Z$21,1,0) -> 0 | AA16: =IF(Y16=1,AA$6*X16*AA$7*Z16,AA$6*X16*AA$8*Z16) -> 0 | AB16: =IF(Y16=1,2%*X16*AA$7*Z16,2%*X16*AA$8*Z16) -> 0 | AC16: 31 | AD16: 1 | AE16: =IF(AE$21,1,0) -> 0 | AF16: =IF(AD16=1,AF$6*AC16*AF$7*AE16,AF$6*AC16*AF$8*AE16) -> 0 | AG16: =IF(AD16=1,2%*AC16*AF$7*AE16,2%*AC16*AF$8*AE16) -> 0 | AH16: 31 | AI16: 1 | AJ16: =IF(AJ$21,1,0) -> 0 | AK16: =IF(AI16=1,AK$6*AH16*AK$7*AJ16,AK$6*AH16*AK$8*AJ16) -> 0 | AL16: =IF(AI16=1,2%*AH16*AK$7*AJ16,2%*AH16*AK$8*AJ16) -> 0 | AM16: 31 | AN16: 1 | AO16: =IF(AO$21,1,0) -> 0 | AP16: =IF(AN16=1,AP$6*AM16*AP$7*AO16,AP$6*AM16*AP$8*AO16) -> 0 | AQ16: =IF(AN16=1,2%*AM16*AP$7*AO16,2%*AM16*AP$8*AO16) -> 0 | AR16: 31 | AS16: 1 | AT16: =IF(AT$21,1,0) -> 0 | AU16: =IF(AS16=1,AU$6*AR16*AU$7*AT16,AU$6*AR16*AU$8*AT16) -> 0 | AV16: =IF(AS16=1,2%*AR16*AU$7*AT16,2%*AR16*AU$8*AT16) -> 0 | AW16: 31 | AX16: 1 | AY16: =IF(AY$21,1,0) -> 0 | AZ16: =IF(AX16=1,AZ$6*AW16*AZ$7*AY16,AZ$6*AW16*AZ$8*AY16) -> 0 | BA16: =IF(AX16=1,2%*AW16*AZ$7*AY16,2%*AW16*AZ$8*AY16) -> 0 | BB16: 31 | BC16: 1 | BD16: =IF(BD$21,1,0) -> 0 | BE16: =IF(BC16=1,BE$6*BB16*BE$7*BD16,BE$6*BB16*BE$8*BD16) -> 0 | BF16: =IF(BC16=1,2%*BB16*BE$7*BD16,2%*BB16*BE$8*BD16) -> 0 | BG16: 31 | BH16: 1 | BI16: =IF(BI$21,1,0) -> 0 | BJ16: =IF(BH16=1,BJ$6*BG16*BJ$7*BI16,BJ$6*BG16*BJ$8*BI16) -> 0 | BK16: =IF(BH16=1,2%*BG16*BJ$7*BI16,2%*BG16*BJ$8*BI16) -> 0 | BL16: 31 | BM16: 1 | BN16: =IF(BN$21,1,0) -> 0 | BO16: =IF(BM16=1,BO$6*BL16*BO$7*BN16,BO$6*BL16*BO$8*BN16) -> 0 | BP16: =IF(BM16=1,2%*BL16*BO$7*BN16,2%*BL16*BO$8*BN16) -> 0 | BQ16: 31 | BR16: 1 | BS16: =IF(BS$21,1,0) -> 0 | BT16: =IF(BR16=1,BT$6*BQ16*BT$7*BS16,BT$6*BQ16*BT$8*BS16) -> 0 | BU16: =IF(BR16=1,2%*BQ16*BT$7*BS16,2%*BQ16*BT$8*BS16) -> 0 | BV16: 31 | BW16: 1 | BX16: =IF(BX$21,1,0) -> 0 | BY16: =IF(BW16=1,BY$6*BV16*BY$7*BX16,BY$6*BV16*BY$8*BX16) -> 0 | BZ16: =IF(BW16=1,2%*BV16*BY$7*BX16,2%*BV16*BY$8*BX16) -> 0 | CA16: 31 | CB16: 1 | CC16: =IF(CC$21,1,0) -> 0 | CD16: =IF(CB16=1,CD$6*CA16*CD$7*CC16,CD$6*CA16*CD$8*CC16) -> 0 | CE16: =IF(CB16=1,2%*CA16*CD$7*CC16,2%*CA16*CD$8*CC16) -> 0 | CF16: 31 | CG16: 1 | CH16: =IF(CH$21,1,0) -> 0 | CI16: =IF(CG16=1,CI$6*CF16*CI$7*CH16,CI$6*CF16*CI$8*CH16) -> 0 | CJ16: =IF(CG16=1,2%*CF16*CI$7*CH16,2%*CF16*CI$8*CH16) -> 0 | CK16: 31 | CL16: 1 | CM16: =IF(CM$21,1,0) -> 0 | CN16: =IF(CL16=1,CN$6*CK16*CN$7*CM16,CN$6*CK16*CN$8*CM16) -> 0 | CO16: =IF(CL16=1,2%*CK16*CN$7*CM16,2%*CK16*CN$8*CM16) -> 0
C17: Septiembre | D17: 30 | E17: 1 | F17: =IF(F$21,1,0) -> 0 | G17: =IF(E17=1,G$6*D17*G$7*F17,G$6*D17*G$8*F17) -> 0 | H17: =IF(E17=1,2%*D17*G$7*F17,2%*D17*G$8*F17) -> 0 | I17: 30 | J17: 1 | K17: =IF(K$21,1,0) -> 0 | L17: =IF(J17=1,L$6*I17*L$7*K17,L$6*I17*L$8*K17) -> 0 | M17: =IF(J17=1,2%*I17*L$7*K17,2%*I17*L$8*K17) -> 0 | N17: 30 | O17: 1 | P17: =IF(P$21,1,0) -> 0 | Q17: =IF(O17=1,Q$6*N17*Q$7*P17,Q$6*N17*Q$8*P17) -> 0 | R17: =IF(O17=1,2%*N17*Q$7*P17,2%*N17*Q$8*P17) -> 0 | S17: 30 | T17: 1 | U17: =IF(U$21,1,0) -> 0 | V17: =IF(T17=1,V$6*S17*V$7*U17,V$6*S17*V$8*U17) -> 0 | W17: =IF(T17=1,2%*S17*V$7*U17,2%*S17*V$8*U17) -> 0 | X17: 30 | Y17: 1 | Z17: =IF(Z$21,1,0) -> 0 | AA17: =IF(Y17=1,AA$6*X17*AA$7*Z17,AA$6*X17*AA$8*Z17) -> 0 | AB17: =IF(Y17=1,2%*X17*AA$7*Z17,2%*X17*AA$8*Z17) -> 0 | AC17: 30 | AD17: 1 | AE17: =IF(AE$21,1,0) -> 0 | AF17: =IF(AD17=1,AF$6*AC17*AF$7*AE17,AF$6*AC17*AF$8*AE17) -> 0 | AG17: =IF(AD17=1,2%*AC17*AF$7*AE17,2%*AC17*AF$8*AE17) -> 0 | AH17: 30 | AI17: 1 | AJ17: =IF(AJ$21,1,0) -> 0 | AK17: =IF(AI17=1,AK$6*AH17*AK$7*AJ17,AK$6*AH17*AK$8*AJ17) -> 0 | AL17: =IF(AI17=1,2%*AH17*AK$7*AJ17,2%*AH17*AK$8*AJ17) -> 0 | AM17: 30 | AN17: 1 | AO17: =IF(AO$21,1,0) -> 0 | AP17: =IF(AN17=1,AP$6*AM17*AP$7*AO17,AP$6*AM17*AP$8*AO17) -> 0 | AQ17: =IF(AN17=1,2%*AM17*AP$7*AO17,2%*AM17*AP$8*AO17) -> 0 | AR17: 30 | AS17: 1 | AT17: =IF(AT$21,1,0) -> 0 | AU17: =IF(AS17=1,AU$6*AR17*AU$7*AT17,AU$6*AR17*AU$8*AT17) -> 0 | AV17: =IF(AS17=1,2%*AR17*AU$7*AT17,2%*AR17*AU$8*AT17) -> 0 | AW17: 30 | AX17: 1 | AY17: =IF(AY$21,1,0) -> 0 | AZ17: =IF(AX17=1,AZ$6*AW17*AZ$7*AY17,AZ$6*AW17*AZ$8*AY17) -> 0 | BA17: =IF(AX17=1,2%*AW17*AZ$7*AY17,2%*AW17*AZ$8*AY17) -> 0 | BB17: 30 | BC17: 1 | BD17: =IF(BD$21,1,0) -> 0 | BE17: =IF(BC17=1,BE$6*BB17*BE$7*BD17,BE$6*BB17*BE$8*BD17) -> 0 | BF17: =IF(BC17=1,2%*BB17*BE$7*BD17,2%*BB17*BE$8*BD17) -> 0 | BG17: 30 | BH17: 1 | BI17: =IF(BI$21,1,0) -> 0 | BJ17: =IF(BH17=1,BJ$6*BG17*BJ$7*BI17,BJ$6*BG17*BJ$8*BI17) -> 0 | BK17: =IF(BH17=1,2%*BG17*BJ$7*BI17,2%*BG17*BJ$8*BI17) -> 0 | BL17: 30 | BM17: 1 | BN17: =IF(BN$21,1,0) -> 0 | BO17: =IF(BM17=1,BO$6*BL17*BO$7*BN17,BO$6*BL17*BO$8*BN17) -> 0 | BP17: =IF(BM17=1,2%*BL17*BO$7*BN17,2%*BL17*BO$8*BN17) -> 0 | BQ17: 30 | BR17: 1 | BS17: =IF(BS$21,1,0) -> 0 | BT17: =IF(BR17=1,BT$6*BQ17*BT$7*BS17,BT$6*BQ17*BT$8*BS17) -> 0 | BU17: =IF(BR17=1,2%*BQ17*BT$7*BS17,2%*BQ17*BT$8*BS17) -> 0 | BV17: 30 | BW17: 1 | BX17: =IF(BX$21,1,0) -> 0 | BY17: =IF(BW17=1,BY$6*BV17*BY$7*BX17,BY$6*BV17*BY$8*BX17) -> 0 | BZ17: =IF(BW17=1,2%*BV17*BY$7*BX17,2%*BV17*BY$8*BX17) -> 0 | CA17: 30 | CB17: 1 | CC17: =IF(CC$21,1,0) -> 0 | CD17: =IF(CB17=1,CD$6*CA17*CD$7*CC17,CD$6*CA17*CD$8*CC17) -> 0 | CE17: =IF(CB17=1,2%*CA17*CD$7*CC17,2%*CA17*CD$8*CC17) -> 0 | CF17: 30 | CG17: 1 | CH17: =IF(CH$21,1,0) -> 0 | CI17: =IF(CG17=1,CI$6*CF17*CI$7*CH17,CI$6*CF17*CI$8*CH17) -> 0 | CJ17: =IF(CG17=1,2%*CF17*CI$7*CH17,2%*CF17*CI$8*CH17) -> 0 | CK17: 30 | CL17: 1 | CM17: =IF(CM$21,1,0) -> 0 | CN17: =IF(CL17=1,CN$6*CK17*CN$7*CM17,CN$6*CK17*CN$8*CM17) -> 0 | CO17: =IF(CL17=1,2%*CK17*CN$7*CM17,2%*CK17*CN$8*CM17) -> 0
C18: Octubre | D18: 31 | E18: 1 | F18: =IF(F$21,1,0) -> 0 | G18: =IF(E18=1,G$6*D18*G$7*F18,G$6*D18*G$8*F18) -> 0 | H18: =IF(E18=1,2%*D18*G$7*F18,2%*D18*G$8*F18) -> 0 | I18: 31 | J18: 1 | K18: =IF(K$21,1,0) -> 0 | L18: =IF(J18=1,L$6*I18*L$7*K18,L$6*I18*L$8*K18) -> 0 | M18: =IF(J18=1,2%*I18*L$7*K18,2%*I18*L$8*K18) -> 0 | N18: 31 | O18: 1 | P18: =IF(P$21,1,0) -> 0 | Q18: =IF(O18=1,Q$6*N18*Q$7*P18,Q$6*N18*Q$8*P18) -> 0 | R18: =IF(O18=1,2%*N18*Q$7*P18,2%*N18*Q$8*P18) -> 0 | S18: 31 | T18: 1 | U18: =IF(U$21,1,0) -> 0 | V18: =IF(T18=1,V$6*S18*V$7*U18,V$6*S18*V$8*U18) -> 0 | W18: =IF(T18=1,2%*S18*V$7*U18,2%*S18*V$8*U18) -> 0 | X18: 31 | Y18: 1 | Z18: =IF(Z$21,1,0) -> 0 | AA18: =IF(Y18=1,AA$6*X18*AA$7*Z18,AA$6*X18*AA$8*Z18) -> 0 | AB18: =IF(Y18=1,2%*X18*AA$7*Z18,2%*X18*AA$8*Z18) -> 0 | AC18: 31 | AD18: 1 | AE18: =IF(AE$21,1,0) -> 0 | AF18: =IF(AD18=1,AF$6*AC18*AF$7*AE18,AF$6*AC18*AF$8*AE18) -> 0 | AG18: =IF(AD18=1,2%*AC18*AF$7*AE18,2%*AC18*AF$8*AE18) -> 0 | AH18: 31 | AI18: 1 | AJ18: =IF(AJ$21,1,0) -> 0 | AK18: =IF(AI18=1,AK$6*AH18*AK$7*AJ18,AK$6*AH18*AK$8*AJ18) -> 0 | AL18: =IF(AI18=1,2%*AH18*AK$7*AJ18,2%*AH18*AK$8*AJ18) -> 0 | AM18: 31 | AN18: 1 | AO18: =IF(AO$21,1,0) -> 0 | AP18: =IF(AN18=1,AP$6*AM18*AP$7*AO18,AP$6*AM18*AP$8*AO18) -> 0 | AQ18: =IF(AN18=1,2%*AM18*AP$7*AO18,2%*AM18*AP$8*AO18) -> 0 | AR18: 31 | AS18: 1 | AT18: =IF(AT$21,1,0) -> 0 | AU18: =IF(AS18=1,AU$6*AR18*AU$7*AT18,AU$6*AR18*AU$8*AT18) -> 0 | AV18: =IF(AS18=1,2%*AR18*AU$7*AT18,2%*AR18*AU$8*AT18) -> 0 | AW18: 31 | AX18: 1 | AY18: =IF(AY$21,1,0) -> 0 | AZ18: =IF(AX18=1,AZ$6*AW18*AZ$7*AY18,AZ$6*AW18*AZ$8*AY18) -> 0 | BA18: =IF(AX18=1,2%*AW18*AZ$7*AY18,2%*AW18*AZ$8*AY18) -> 0 | BB18: 31 | BC18: 1 | BD18: =IF(BD$21,1,0) -> 0 | BE18: =IF(BC18=1,BE$6*BB18*BE$7*BD18,BE$6*BB18*BE$8*BD18) -> 0 | BF18: =IF(BC18=1,2%*BB18*BE$7*BD18,2%*BB18*BE$8*BD18) -> 0 | BG18: 31 | BH18: 1 | BI18: =IF(BI$21,1,0) -> 0 | BJ18: =IF(BH18=1,BJ$6*BG18*BJ$7*BI18,BJ$6*BG18*BJ$8*BI18) -> 0 | BK18: =IF(BH18=1,2%*BG18*BJ$7*BI18,2%*BG18*BJ$8*BI18) -> 0 | BL18: 31 | BM18: 1 | BN18: =IF(BN$21,1,0) -> 0 | BO18: =IF(BM18=1,BO$6*BL18*BO$7*BN18,BO$6*BL18*BO$8*BN18) -> 0 | BP18: =IF(BM18=1,2%*BL18*BO$7*BN18,2%*BL18*BO$8*BN18) -> 0 | BQ18: 31 | BR18: 1 | BS18: =IF(BS$21,1,0) -> 0 | BT18: =IF(BR18=1,BT$6*BQ18*BT$7*BS18,BT$6*BQ18*BT$8*BS18) -> 0 | BU18: =IF(BR18=1,2%*BQ18*BT$7*BS18,2%*BQ18*BT$8*BS18) -> 0 | BV18: 31 | BW18: 1 | BX18: =IF(BX$21,1,0) -> 0 | BY18: =IF(BW18=1,BY$6*BV18*BY$7*BX18,BY$6*BV18*BY$8*BX18) -> 0 | BZ18: =IF(BW18=1,2%*BV18*BY$7*BX18,2%*BV18*BY$8*BX18) -> 0 | CA18: 31 | CB18: 1 | CC18: =IF(CC$21,1,0) -> 0 | CD18: =IF(CB18=1,CD$6*CA18*CD$7*CC18,CD$6*CA18*CD$8*CC18) -> 0 | CE18: =IF(CB18=1,2%*CA18*CD$7*CC18,2%*CA18*CD$8*CC18) -> 0 | CF18: 31 | CG18: 1 | CH18: =IF(CH$21,1,0) -> 0 | CI18: =IF(CG18=1,CI$6*CF18*CI$7*CH18,CI$6*CF18*CI$8*CH18) -> 0 | CJ18: =IF(CG18=1,2%*CF18*CI$7*CH18,2%*CF18*CI$8*CH18) -> 0 | CK18: 31 | CL18: 1 | CM18: =IF(CM$21,1,0) -> 0 | CN18: =IF(CL18=1,CN$6*CK18*CN$7*CM18,CN$6*CK18*CN$8*CM18) -> 0 | CO18: =IF(CL18=1,2%*CK18*CN$7*CM18,2%*CK18*CN$8*CM18) -> 0
C19: Noviembre | D19: 30 | E19: 1 | F19: =IF(F$21,1,0) -> 0 | G19: =IF(E19=1,G$6*D19*G$7*F19,G$6*D19*G$8*F19) -> 0 | H19: =IF(E19=1,2%*D19*G$7*F19,2%*D19*G$8*F19) -> 0 | I19: 30 | J19: 1 | K19: =IF(K$21,1,0) -> 0 | L19: =IF(J19=1,L$6*I19*L$7*K19,L$6*I19*L$8*K19) -> 0 | M19: =IF(J19=1,2%*I19*L$7*K19,2%*I19*L$8*K19) -> 0 | N19: 30 | O19: 1 | P19: =IF(P$21,1,0) -> 0 | Q19: =IF(O19=1,Q$6*N19*Q$7*P19,Q$6*N19*Q$8*P19) -> 0 | R19: =IF(O19=1,2%*N19*Q$7*P19,2%*N19*Q$8*P19) -> 0 | S19: 30 | T19: 1 | U19: =IF(U$21,1,0) -> 0 | V19: =IF(T19=1,V$6*S19*V$7*U19,V$6*S19*V$8*U19) -> 0 | W19: =IF(T19=1,2%*S19*V$7*U19,2%*S19*V$8*U19) -> 0 | X19: 30 | Y19: 1 | Z19: =IF(Z$21,1,0) -> 0 | AA19: =IF(Y19=1,AA$6*X19*AA$7*Z19,AA$6*X19*AA$8*Z19) -> 0 | AB19: =IF(Y19=1,2%*X19*AA$7*Z19,2%*X19*AA$8*Z19) -> 0 | AC19: 30 | AD19: 1 | AE19: =IF(AE$21,1,0) -> 0 | AF19: =IF(AD19=1,AF$6*AC19*AF$7*AE19,AF$6*AC19*AF$8*AE19) -> 0 | AG19: =IF(AD19=1,2%*AC19*AF$7*AE19,2%*AC19*AF$8*AE19) -> 0 | AH19: 30 | AI19: 1 | AJ19: =IF(AJ$21,1,0) -> 0 | AK19: =IF(AI19=1,AK$6*AH19*AK$7*AJ19,AK$6*AH19*AK$8*AJ19) -> 0 | AL19: =IF(AI19=1,2%*AH19*AK$7*AJ19,2%*AH19*AK$8*AJ19) -> 0 | AM19: 30 | AN19: 1 | AO19: =IF(AO$21,1,0) -> 0 | AP19: =IF(AN19=1,AP$6*AM19*AP$7*AO19,AP$6*AM19*AP$8*AO19) -> 0 | AQ19: =IF(AN19=1,2%*AM19*AP$7*AO19,2%*AM19*AP$8*AO19) -> 0 | AR19: 30 | AS19: 1 | AT19: =IF(AT$21,1,0) -> 0 | AU19: =IF(AS19=1,AU$6*AR19*AU$7*AT19,AU$6*AR19*AU$8*AT19) -> 0 | AV19: =IF(AS19=1,2%*AR19*AU$7*AT19,2%*AR19*AU$8*AT19) -> 0 | AW19: 30 | AX19: 1 | AY19: =IF(AY$21,1,0) -> 0 | AZ19: =IF(AX19=1,AZ$6*AW19*AZ$7*AY19,AZ$6*AW19*AZ$8*AY19) -> 0 | BA19: =IF(AX19=1,2%*AW19*AZ$7*AY19,2%*AW19*AZ$8*AY19) -> 0 | BB19: 30 | BC19: 1 | BD19: =IF(BD$21,1,0) -> 0 | BE19: =IF(BC19=1,BE$6*BB19*BE$7*BD19,BE$6*BB19*BE$8*BD19) -> 0 | BF19: =IF(BC19=1,2%*BB19*BE$7*BD19,2%*BB19*BE$8*BD19) -> 0 | BG19: 30 | BH19: 1 | BI19: =IF(BI$21,1,0) -> 0 | BJ19: =IF(BH19=1,BJ$6*BG19*BJ$7*BI19,BJ$6*BG19*BJ$8*BI19) -> 0 | BK19: =IF(BH19=1,2%*BG19*BJ$7*BI19,2%*BG19*BJ$8*BI19) -> 0 | BL19: 30 | BM19: 1 | BN19: =IF(BN$21,1,0) -> 0 | BO19: =IF(BM19=1,BO$6*BL19*BO$7*BN19,BO$6*BL19*BO$8*BN19) -> 0 | BP19: =IF(BM19=1,2%*BL19*BO$7*BN19,2%*BL19*BO$8*BN19) -> 0 | BQ19: 30 | BR19: 1 | BS19: =IF(BS$21,1,0) -> 0 | BT19: =IF(BR19=1,BT$6*BQ19*BT$7*BS19,BT$6*BQ19*BT$8*BS19) -> 0 | BU19: =IF(BR19=1,2%*BQ19*BT$7*BS19,2%*BQ19*BT$8*BS19) -> 0 | BV19: 30 | BW19: 1 | BX19: =IF(BX$21,1,0) -> 0 | BY19: =IF(BW19=1,BY$6*BV19*BY$7*BX19,BY$6*BV19*BY$8*BX19) -> 0 | BZ19: =IF(BW19=1,2%*BV19*BY$7*BX19,2%*BV19*BY$8*BX19) -> 0 | CA19: 30 | CB19: 1 | CC19: =IF(CC$21,1,0) -> 0 | CD19: =IF(CB19=1,CD$6*CA19*CD$7*CC19,CD$6*CA19*CD$8*CC19) -> 0 | CE19: =IF(CB19=1,2%*CA19*CD$7*CC19,2%*CA19*CD$8*CC19) -> 0 | CF19: 30 | CG19: 1 | CH19: =IF(CH$21,1,0) -> 0 | CI19: =IF(CG19=1,CI$6*CF19*CI$7*CH19,CI$6*CF19*CI$8*CH19) -> 0 | CJ19: =IF(CG19=1,2%*CF19*CI$7*CH19,2%*CF19*CI$8*CH19) -> 0 | CK19: 30 | CL19: 1 | CM19: =IF(CM$21,1,0) -> 0 | CN19: =IF(CL19=1,CN$6*CK19*CN$7*CM19,CN$6*CK19*CN$8*CM19) -> 0 | CO19: =IF(CL19=1,2%*CK19*CN$7*CM19,2%*CK19*CN$8*CM19) -> 0
C20: Diciembre | D20: 31 | E20: 1 | F20: =IF(F$21,1,0) -> 0 | G20: =IF(E20=1,G$6*D20*G$7*F20,G$6*D20*G$8*F20) -> 0 | H20: =IF(E20=1,2%*D20*G$7*F20,2%*D20*G$8*F20) -> 0 | I20: 31 | J20: 1 | K20: =IF(K$21,1,0) -> 0 | L20: =IF(J20=1,L$6*I20*L$7*K20,L$6*I20*L$8*K20) -> 0 | M20: =IF(J20=1,2%*I20*L$7*K20,2%*I20*L$8*K20) -> 0 | N20: 31 | O20: 1 | P20: =IF(P$21,1,0) -> 0 | Q20: =IF(O20=1,Q$6*N20*Q$7*P20,Q$6*N20*Q$8*P20) -> 0 | R20: =IF(O20=1,2%*N20*Q$7*P20,2%*N20*Q$8*P20) -> 0 | S20: 31 | T20: 1 | U20: =IF(U$21,1,0) -> 0 | V20: =IF(T20=1,V$6*S20*V$7*U20,V$6*S20*V$8*U20) -> 0 | W20: =IF(T20=1,2%*S20*V$7*U20,2%*S20*V$8*U20) -> 0 | X20: 31 | Y20: 1 | Z20: =IF(Z$21,1,0) -> 0 | AA20: =IF(Y20=1,AA$6*X20*AA$7*Z20,AA$6*X20*AA$8*Z20) -> 0 | AB20: =IF(Y20=1,2%*X20*AA$7*Z20,2%*X20*AA$8*Z20) -> 0 | AC20: 31 | AD20: 1 | AE20: =IF(AE$21,1,0) -> 0 | AF20: =IF(AD20=1,AF$6*AC20*AF$7*AE20,AF$6*AC20*AF$8*AE20) -> 0 | AG20: =IF(AD20=1,2%*AC20*AF$7*AE20,2%*AC20*AF$8*AE20) -> 0 | AH20: 31 | AI20: 1 | AJ20: =IF(AJ$21,1,0) -> 0 | AK20: =IF(AI20=1,AK$6*AH20*AK$7*AJ20,AK$6*AH20*AK$8*AJ20) -> 0 | AL20: =IF(AI20=1,2%*AH20*AK$7*AJ20,2%*AH20*AK$8*AJ20) -> 0 | AM20: 31 | AN20: 1 | AO20: =IF(AO$21,1,0) -> 0 | AP20: =IF(AN20=1,AP$6*AM20*AP$7*AO20,AP$6*AM20*AP$8*AO20) -> 0 | AQ20: =IF(AN20=1,2%*AM20*AP$7*AO20,2%*AM20*AP$8*AO20) -> 0 | AR20: 31 | AS20: 1 | AT20: =IF(AT$21,1,0) -> 0 | AU20: =IF(AS20=1,AU$6*AR20*AU$7*AT20,AU$6*AR20*AU$8*AT20) -> 0 | AV20: =IF(AS20=1,2%*AR20*AU$7*AT20,2%*AR20*AU$8*AT20) -> 0 | AW20: 31 | AX20: 1 | AY20: =IF(AY$21,1,0) -> 0 | AZ20: =IF(AX20=1,AZ$6*AW20*AZ$7*AY20,AZ$6*AW20*AZ$8*AY20) -> 0 | BA20: =IF(AX20=1,2%*AW20*AZ$7*AY20,2%*AW20*AZ$8*AY20) -> 0 | BB20: 31 | BC20: 1 | BD20: =IF(BD$21,1,0) -> 0 | BE20: =IF(BC20=1,BE$6*BB20*BE$7*BD20,BE$6*BB20*BE$8*BD20) -> 0 | BF20: =IF(BC20=1,2%*BB20*BE$7*BD20,2%*BB20*BE$8*BD20) -> 0 | BG20: 31 | BH20: 1 | BI20: =IF(BI$21,1,0) -> 0 | BJ20: =IF(BH20=1,BJ$6*BG20*BJ$7*BI20,BJ$6*BG20*BJ$8*BI20) -> 0 | BK20: =IF(BH20=1,2%*BG20*BJ$7*BI20,2%*BG20*BJ$8*BI20) -> 0 | BL20: 31 | BM20: 1 | BN20: =IF(BN$21,1,0) -> 0 | BO20: =IF(BM20=1,BO$6*BL20*BO$7*BN20,BO$6*BL20*BO$8*BN20) -> 0 | BP20: =IF(BM20=1,2%*BL20*BO$7*BN20,2%*BL20*BO$8*BN20) -> 0 | BQ20: 31 | BR20: 1 | BS20: =IF(BS$21,1,0) -> 0 | BT20: =IF(BR20=1,BT$6*BQ20*BT$7*BS20,BT$6*BQ20*BT$8*BS20) -> 0 | BU20: =IF(BR20=1,2%*BQ20*BT$7*BS20,2%*BQ20*BT$8*BS20) -> 0 | BV20: 31 | BW20: 1 | BX20: =IF(BX$21,1,0) -> 0 | BY20: =IF(BW20=1,BY$6*BV20*BY$7*BX20,BY$6*BV20*BY$8*BX20) -> 0 | BZ20: =IF(BW20=1,2%*BV20*BY$7*BX20,2%*BV20*BY$8*BX20) -> 0 | CA20: 31 | CB20: 1 | CC20: =IF(CC$21,1,0) -> 0 | CD20: =IF(CB20=1,CD$6*CA20*CD$7*CC20,CD$6*CA20*CD$8*CC20) -> 0 | CE20: =IF(CB20=1,2%*CA20*CD$7*CC20,2%*CA20*CD$8*CC20) -> 0 | CF20: 31 | CG20: 1 | CH20: =IF(CH$21,1,0) -> 0 | CI20: =IF(CG20=1,CI$6*CF20*CI$7*CH20,CI$6*CF20*CI$8*CH20) -> 0 | CJ20: =IF(CG20=1,2%*CF20*CI$7*CH20,2%*CF20*CI$8*CH20) -> 0 | CK20: 31 | CL20: 1 | CM20: =IF(CM$21,1,0) -> 0 | CN20: =IF(CL20=1,CN$6*CK20*CN$7*CM20,CN$6*CK20*CN$8*CM20) -> 0 | CO20: =IF(CL20=1,2%*CK20*CN$7*CM20,2%*CK20*CN$8*CM20) -> 0
C21: Inversión Anual: | F21: FALSE | G21: =SUM(G9:G20) -> 0 | K21: FALSE | L21: =SUM(L9:L20) -> 0 | P21: FALSE | Q21: =SUM(Q9:Q20) -> 0 | U21: FALSE | V21: =SUM(V9:V20) -> 0 | Z21: FALSE | AA21: =SUM(AA9:AA20) -> 0 | AE21: FALSE | AF21: =SUM(AF9:AF20) -> 0 | AJ21: FALSE | AK21: =SUM(AK9:AK20) -> 0 | AO21: FALSE | AP21: =SUM(AP9:AP20) -> 0 | AT21: FALSE | AU21: =SUM(AU9:AU20) -> 0 | AY21: FALSE | AZ21: =SUM(AZ9:AZ20) -> 0 | BD21: FALSE | BE21: =SUM(BE9:BE20) -> 0 | BI21: FALSE | BJ21: =SUM(BJ9:BJ20) -> 0 | BN21: FALSE | BO21: =SUM(BO9:BO20) -> 0 | BS21: FALSE | BT21: =SUM(BT9:BT20) -> 0 | BX21: FALSE | BY21: =SUM(BY9:BY20) -> 0 | CC21: FALSE | CD21: =SUM(CD9:CD20) -> 0 | CH21: FALSE | CI21: =SUM(CI9:CI20) -> 0 | CM21: FALSE | CN21: =SUM(CN9:CN20) -> 0
C22: Monto anual al fondo de Retiro: | G22: =SUM(H9:H20) -> 0 | L22: =SUM(M9:M20) -> 0 | Q22: =SUM(R9:R20) -> 0 | V22: =SUM(W9:W20) -> 0 | AA22: =SUM(AB9:AB20) -> 0 | AF22: =SUM(AG9:AG20) -> 0 | AK22: =SUM(AL9:AL20) -> 0 | AP22: =SUM(AQ9:AQ20) -> 0 | AU22: =SUM(AV9:AV20) -> 0 | AZ22: =SUM(BA9:BA20) -> 0 | BE22: =SUM(BF9:BF20) -> 0 | BJ22: =SUM(BK9:BK20) -> 0 | BO22: =SUM(BP9:BP20) -> 0 | BT22: =SUM(BU9:BU20) -> 0 | BY22: =SUM(BZ9:BZ20) -> 0 | CD22: =SUM(CE9:CE20) -> 0 | CI22: =SUM(CJ9:CJ20) -> 0 | CN22: =SUM(CO9:CO20) -> 0
C23: Días totales del año: | G23: =(D9*F9)+(D10*F10)+(D11*F11)+(D12*F12)+(D13*F13)+(D14*F14)+(D15*F15)+(D16*F16)+(D17*F17)+(D18*F18)+(D19*F19)+(D20*F20) -> 0 | L23: =(I9*K9)+(I10*K10)+(I11*K11)+(I12*K12)+(I13*K13)+(I14*K14)+(I15*K15)+(I16*K16)+(I17*K17)+(I18*K18)+(I19*K19)+(I20*K20) -> 0 | Q23: =(N9*P9)+(N10*P10)+(N11*P11)+(N12*P12)+(N13*P13)+(N14*P14)+(N15*P15)+(N16*P16)+(N17*P17)+(N18*P18)+(N19*P19)+(N20*P20) -> 0 | V23: =(S9*U9)+(S10*U10)+(S11*U11)+(S12*U12)+(S13*U13)+(S14*U14)+(S15*U15)+(S16*U16)+(S17*U17)+(S18*U18)+(S19*U19)+(S20*U20) -> 0 | AA23: =(X9*Z9)+(X10*Z10)+(X11*Z11)+(X12*Z12)+(X13*Z13)+(X14*Z14)+(X15*Z15)+(X16*Z16)+(X17*Z17)+(X18*Z18)+(X19*Z19)+(X20*Z20) -> 0 | AF23: =(AC9*AE9)+(AC10*AE10)+(AC11*AE11)+(AC12*AE12)+(AC13*AE13)+(AC14*AE14)+(AC15*AE15)+(AC16*AE16)+(AC17*AE17)+(AC18*AE18)+(AC19*AE19)+(AC20*AE20) -> 0 | AK23: =(AH9*AJ9)+(AH10*AJ10)+(AH11*AJ11)+(AH12*AJ12)+(AH13*AJ13)+(AH14*AJ14)+(AH15*AJ15)+(AH16*AJ16)+(AH17*AJ17)+(AH18*AJ18)+(AH19*AJ19)+(AH20*AJ20) -> 0 | AP23: =(AM9*AO9)+(AM10*AO10)+(AM11*AO11)+(AM12*AO12)+(AM13*AO13)+(AM14*AO14)+(AM15*AO15)+(AM16*AO16)+(AM17*AO17)+(AM18*AO18)+(AM19*AO19)+(AM20*AO20) -> 0 | AU23: =(AR9*AT9)+(AR10*AT10)+(AR11*AT11)+(AR12*AT12)+(AR13*AT13)+(AR14*AT14)+(AR15*AT15)+(AR16*AT16)+(AR17*AT17)+(AR18*AT18)+(AR19*AT19)+(AR20*AT20) -> 0 | AZ23: =(AW9*AY9)+(AW10*AY10)+(AW11*AY11)+(AW12*AY12)+(AW13*AY13)+(AW14*AY14)+(AW15*AY15)+(AW16*AY16)+(AW17*AY17)+(AW18*AY18)+(AW19*AY19)+(AW20*AY20) -> 0 | BE23: =(BB9*BD9)+(BB10*BD10)+(BB11*BD11)+(BB12*BD12)+(BB13*BD13)+(BB14*BD14)+(BB15*BD15)+(BB16*BD16)+(BB17*BD17)+(BB18*BD18)+(BB19*BD19)+(BB20*BD20) -> 0 | BJ23: =(BG9*BI9)+(BG10*BI10)+(BG11*BI11)+(BG12*BI12)+(BG13*BI13)+(BG14*BI14)+(BG15*BI15)+(BG16*BI16)+(BG17*BI17)+(BG18*BI18)+(BG19*BI19)+(BG20*BI20) -> 0 | BO23: =(BL9*BN9)+(BL10*BN10)+(BL11*BN11)+(BL12*BN12)+(BL13*BN13)+(BL14*BN14)+(BL15*BN15)+(BL16*BN16)+(BL17*BN17)+(BL18*BN18)+(BL19*BN19)+(BL20*BN20) -> 0 | BT23: =(BQ9*BS9)+(BQ10*BS10)+(BQ11*BS11)+(BQ12*BS12)+(BQ13*BS13)+(BQ14*BS14)+(BQ15*BS15)+(BQ16*BS16)+(BQ17*BS17)+(BQ18*BS18)+(BQ19*BS19)+(BQ20*BS20) -> 0 | BY23: =(BV9*BX9)+(BV10*BX10)+(BV11*BX11)+(BV12*BX12)+(BV13*BX13)+(BV14*BX14)+(BV15*BX15)+(BV16*BX16)+(BV17*BX17)+(BV18*BX18)+(BV19*BX19)+(BV20*BX20) -> 0 | CD23: =(CA9*CC9)+(CA10*CC10)+(CA11*CC11)+(CA12*CC12)+(CA13*CC13)+(CA14*CC14)+(CA15*CC15)+(CA16*CC16)+(CA17*CC17)+(CA18*CC18)+(CA19*CC19)+(CA20*CC20) -> 0 | CI23: =(CF9*CH9)+(CF10*CH10)+(CF11*CH11)+(CF12*CH12)+(CF13*CH13)+(CF14*CH14)+(CF15*CH15)+(CF16*CH16)+(CF17*CH17)+(CF18*CH18)+(CF19*CH19)+(CF20*CH20) -> 0 | CN23: =(CK9*CM9)+(CK10*CM10)+(CK11*CM11)+(CK12*CM12)+(CK13*CM13)+(CK14*CM14)+(CK15*CM15)+(CK16*CM16)+(CK17*CM17)+(CK18*CM18)+(CK19*CM19)+(CK20*CM20) -> 0
C25: Monto total de la inversión: | G25: =G21+L21+AF21+AK21+AP21+AU21+AZ21+BE21+BJ21+BO21+Q21+V21+AA21+BT21+BY21+CD21+CI21+CN21 -> 0
C26: Monto total al fondo de Retiro: | G26: =G22+L22+AF22+AK22+AP22+AU22+AZ22+BE22+BJ22+BO22+Q22+V22+AA22+BT22+BY22+CD22+CI22+CN22 -> 0
C27: Diás adicionales: | G27: =G23+L23+AF23+AK23+AP23+AU23+AZ23+BE23+BJ23+BO23+Q23+V23+AA23+BT23+BY23+CD23+CI23+CN23 -> 0
C28: Semanas adicionales: | G28: =TRUNC(G27/7) -> 0

Sheet TblDePagosMod40
D3: 0.10075 | K3: 0.10075 | R3: 0.10075 | Y3: 0.10075 | AF3: 0.10075 | AM3: 0.10075 | AT3: 0.11166 | BA3: 0.12256 | BH3: 0.13347 | BO3: 0.14438 | BV3: 0.15528 | CC3: 0.16619 | CJ3: 0.17709 | CQ3: 0.188 | CX3: 0.188 | DE3: 0.188 | DL3: 0.188 | DS3: 0.188 | DZ3: 0.188
B4: Cantidad de UMAs | C4: Valor de la UMA | D4: Pago Díario | E4: Pago de 28 días | F4: Pago de 30 días | G4: Pago de 31 días | I4: Cantidad de UMAs | J4: Valor de la UMA | K4: Pago Díario | L4: Pago de 28 días | M4: Pago de 30 días | N4: Pago de 31 días | P4: Cantidad de UMAs | Q4: Valor de la UMA | R4: Pago Díario | S4: Pago de 28 días | T4: Pago de 30 días | U4: Pago de 31 días | W4: Cantidad de UMAs | X4: Valor de la UMA | Y4: Pago Díario | Z4: Pago de 29 días | AA4: Pago de 30 días | AB4: Pago de 31 días | AD4: Cantidad de UMAs | AE4: Valor de la UMA | AF4: Pago Díario | AG4: Pago de 28 días | AH4: Pago de 30 días | AI4: Pago de 31 días | AK4: Cantidad de UMAs | AL4: Valor de la UMA | AM4: Pago Díario | AN4: Pago de 28 días | AO4: Pago de 30 días | AP4: Pago de 31 días | AR4: Cantidad de UMAs | AS4: Valor de la UMA | AT4: Pago Díario | AU4: Pago de 28 días | AV4: Pago de 30 días | AW4: Pago de 31 días | AY4: Cantidad de UMAs | AZ4: Valor de la UMA | BA4: Pago Díario | BB4: Pago de 29 días | BC4: Pago de 30 días | BD4: Pago de 31 días | BF4: Cantidad de UMAs | BG4: Valor de la UMA | BH4: Pago Díario | BI4: Pago de 28 días | BJ4: Pago de 30 días | BK4: Pago de 31 días | BM4: Cantidad de UMAs | BN4: Valor de la UMA | BO4: Pago Díario | BP4: Pago de 28 días | BQ4: Pago de 30 días | BR4: Pago de 31 días | BT4: Cantidad de UMAs | BU4: Valor de la UMA | BV4: Pago Díario | BW4: Pago de 28 días | BX4: Pago de 30 días | BY4: Pago de 31 días | CA4: Cantidad de UMAs | CB4: Valor de la UMA | CC4: Pago Díario | CD4: Pago de 29 días | CE4: Pago de 30 días | CF4: Pago de 31 días | CH4: Cantidad de UMAs | CI4: Valor de la UMA | CJ4: Pago Díario | CK4: Pago de 28 días | CL4: Pago de 30 días | CM4: Pago de 31 días | CO4: Cantidad de UMAs | CP4: Valor de la UMA | CQ4: Pago Díario | CR4: Pago de 28 días | CS4: Pago de 30 días | CT4: Pago de 31 días | CV4: Cantidad de UMAs | CW4: Valor de la UMA | CX4: Pago Díario | CY4: Pago de 28 días | CZ4: Pago de 30 días | DA4: Pago de 31 días | DC4: Cantidad de UMAs | DD4: Valor de la UMA | DE4: Pago Díario | DF4: Pago de 28 días | DG4: Pago de 30 días | DH4: Pago de 31 días | DJ4: Cantidad de UMAs | DK4: Valor de la UMA | DL4: Pago Díario | DM4: Pago de 28 días | DN4: Pago de 30 días | DO4: Pago de 31 días | DQ4: Cantidad de UMAs | DR4: Valor de la UMA | DS4: Pago Díario | DT4: Pago de 28 días | DU4: Pago de 30 días | DV4: Pago de 31 días | DX4: Cantidad de UMAs | DY4: Valor de la UMA | DZ4: Pago Díario | EA4: Pago de 28 días | EB4: Pago de 30 días | EC4: Pago de 31 días
B5: 1 | C5: 75.49 | D5: =C5*D$3 -> 7.6056175 | E5: =D5*28 -> 212.95729 | F5: =D5*30 -> 228.16853 | G5: =D5*31 -> 235.77414 | I5: 1 | J5: 80.6 | K5: =J5*K$3 -> 8.12045 | L5: =K5*28 -> 227.3726 | M5: =K5*30 -> 243.6135 | N5: =K5*31 -> 251.73395 | P5: 1 | Q5: 84.49 | R5: =Q5*R$3 -> 8.5123675 | S5: =R5*28 -> 238.34629 | T5: =R5*30 -> 255.37103 | U5: =R5*31 -> 263.88339 | W5: 1 | X5: 86.88 | Y5: =X5*Y$3 -> 8.75316 | Z5: =Y5*28 -> 245.08848 | AA5: =Y5*30 -> 262.5948 | AB5: =Y5*31 -> 271.34796 | AD5: 1 | AE5: 89.62 | AF5: =AE5*AF$3 -> 9.029215 | AG5: =AF5*28 -> 252.81802 | AH5: =AF5*30 -> 270.87645 | AI5: =AF5*31 -> 279.90566 | AK5: 1 | AL5: 96.22 | AM5: =AL5*AM$3 -> 9.694165 | AN5: =AM5*28 -> 271.43662 | AO5: =AM5*30 -> 290.82495 | AP5: =AM5*31 -> 300.51911 | AR5: 1 | AS5: 103.74 | AT5: =AS5*AT$3 -> 11.583608 | AU5: =AT5*28 -> 324.34104 | AV5: =AT5*30 -> 347.50825 | AW5: =AT5*31 -> 359.09186 | AY5: 1 | AZ5: 0 | BA5: =AZ5*BA$3 -> 0 | BB5: =BA5*28 -> 0 | BC5: =BA5*30 -> 0 | BD5: =BA5*31 -> 0 | BF5: 1 | BG5: 0 | BH5: =BG5*BH$3 -> 0 | BI5: =BH5*28 -> 0 | BJ5: =BH5*30 -> 0 | BK5: =BH5*31 -> 0 | BM5: 1 | BN5: 0 | BO5: =BN5*BO$3 -> 0 | BP5: =BO5*28 -> 0 | BQ5: =BO5*30 -> 0 | BR5: =BO5*31 -> 0 | BT5: 1 | BU5: 0 | BV5: =BU5*BV$3 -> 0 | BW5: =BV5*28 -> 0 | BX5: =BV5*30 -> 0 | BY5: =BV5*31 -> 0 | CA5: 1 | CB5: 0 | CC5: =CB5*CC$3 -> 0 | CD5: =CC5*28 -> 0 | CE5: =CC5*30 -> 0 | CF5: =CC5*31 -> 0 | CH5: 1 | CI5: 0 | CJ5: =CI5*CJ$3 -> 0 | CK5: =CJ5*28 -> 0 | CL5: =CJ5*30 -> 0 | CM5: =CJ5*31 -> 0 | CO5: 1 | CP5: 0 | CQ5: =CP5*CQ$3 -> 0 | CR5: =CQ5*28 -> 0 | CS5: =CQ5*30 -> 0 | CT5: =CQ5*31 -> 0 | CV5: 1 | CW5: 0 | CX5: =CW5*CX$3 -> 0 | CY5: =CX5*28 -> 0 | CZ5: =CX5*30 -> 0 | DA5: =CX5*31 -> 0 | DC5: 1 | DD5: 0 | DE5: =DD5*DE$3 -> 0 | DF5: =DE5*28 -> 0 | DG5: =DE5*30 -> 0 | DH5: =DE5*31 -> 0 | DJ5: 1 | DK5: 0 | DL5: =DK5*DL$3 -> 0 | DM5: =DL5*28 -> 0 | DN5: =DL5*30 -> 0 | DO5: =DL5*31 -> 0 | DQ5: 1 | DR5: 0 | DS5: =DR5*DS$3 -> 0 | DT5: =DS5*28 -> 0 | DU5: =DS5*30 -> 0 | DV5: =DS5*31 -> 0 | DX5: 1 | DY5: 0 | DZ5: =DY5*DZ$3 -> 0 | EA5: =DZ5*28 -> 0 | EB5: =DZ5*30 -> 0 | EC5: =DZ5*31 -> 0
B6: 2 | C6: =C$5*B6 -> 150.98 | D6: =C6*D$3 -> 15.211235 | E6: =D6*28 -> 425.91458 | F6: =D6*30 -> 456.33705 | G6: =D6*31 -> 471.54829 | I6: 2 | J6: =J$5*I6 -> 161.2 | K6: =J6*K$3 -> 16.2409 | L6: =K6*28 -> 454.7452 | M6: =K6*30 -> 487.227 | N6: =K6*31 -> 503.4679 | P6: 2 | Q6: =Q$5*P6 -> 168.98 | R6: =Q6*R$3 -> 17.024735 | S6: =R6*28 -> 476.69258 | T6: =R6*30 -> 510.74205 | U6: =R6*31 -> 527.76679 | W6: 2 | X6: =X$5*W6 -> 173.76 | Y6: =X6*Y$3 -> 17.50632 | Z6: =Y6*29 -> 507.68328 | AA6: =Y6*30 -> 525.1896 | AB6: =Y6*31 -> 542.69592 | AD6: 2 | AE6: =AE$5*AD6 -> 179.24 | AF6: =AE6*AF$3 -> 18.05843 | AG6: =AF6*28 -> 505.63604 | AH6: =AF6*30 -> 541.7529 | AI6: =AF6*31 -> 559.81133 | AK6: 2 | AL6: =AL$5*AK6 -> 192.44 | AM6: =AL6*AM$3 -> 19.38833 | AN6: =AM6*28 -> 542.87324 | AO6: =AM6*30 -> 581.6499 | AP6: =AM6*31 -> 601.03823 | AR6: 2 | AS6: =AS$5*AR6 -> 207.48 | AT6: =AS6*AT$3 -> 23.167217 | AU6: =AT6*28 -> 648.68207 | AV6: =AT6*30 -> 695.0165 | AW6: =AT6*31 -> 718.18372 | AY6: 2 | AZ6: =AZ$5*AY6 -> 0 | BA6: =AZ6*BA$3 -> 0 | BB6: =BA6*29 -> 0 | BC6: =BA6*30 -> 0 | BD6: =BA6*31 -> 0 | BF6: 2 | BG6: =BG$5*BF6 -> 0 | BH6: =BG6*BH$3 -> 0 | BI6: =BH6*28 -> 0 | BJ6: =BH6*30 -> 0 | BK6: =BH6*31 -> 0 | BM6: 2 | BN6: =BN$5*BM6 -> 0 | BO6: =BN6*BO$3 -> 0 | BP6: =BO6*28 -> 0 | BQ6: =BO6*30 -> 0 | BR6: =BO6*31 -> 0 | BT6: 2 | BU6: =BU$5*BT6 -> 0 | BV6: =BU6*BV$3 -> 0 | BW6: =BV6*28 -> 0 | BX6: =BV6*30 -> 0 | BY6: =BV6*31 -> 0 | CA6: 2 | CB6: =CB$5*CA6 -> 0 | CC6: =CB6*CC$3 -> 0 | CD6: =CC6*29 -> 0 | CE6: =CC6*30 -> 0 | CF6: =CC6*31 -> 0 | CH6: 2 | CI6: =CI$5*CH6 -> 0 | CJ6: =CI6*CJ$3 -> 0 | CK6: =CJ6*28 -> 0 | CL6: =CJ6*30 -> 0 | CM6: =CJ6*31 -> 0 | CO6: 2 | CP6: =CP$5*CO6 -> 0 | CQ6: =CP6*CQ$3 -> 0 | CR6: =CQ6*28 -> 0 | CS6: =CQ6*30 -> 0 | CT6: =CQ6*31 -> 0 | CV6: 2 | CW6: =CW$5*CV6 -> 0 | CX6: =CW6*CX$3 -> 0 | CY6: =CX6*28 -> 0 | CZ6: =CX6*30 -> 0 | DA6: =CX6*31 -> 0 | DC6: 2 | DD6: =DD$5*DC6 -> 0 | DE6: =DD6*DE$3 -> 0 | DF6: =DE6*28 -> 0 | DG6: =DE6*30 -> 0 | DH6: =DE6*31 -> 0 | DJ6: 2 | DK6: =DK$5*DJ6 -> 0 | DL6: =DK6*DL$3 -> 0 | DM6: =DL6*28 -> 0 | DN6: =DL6*30 -> 0 | DO6: =DL6*31 -> 0 | DQ6: 2 | DR6: =DR$5*DQ6 -> 0 | DS6: =DR6*DS$3 -> 0 | DT6: =DS6*28 -> 0 | DU6: =DS6*30 -> 0 | DV6: =DS6*31 -> 0 | DX6: 2 | DY6: =DY$5*DX6 -> 0 | DZ6: =DY6*DZ$3 -> 0 | EA6: =DZ6*28 -> 0 | EB6: =DZ6*30 -> 0 | EC6: =DZ6*31 -> 0
B7: 3 | C7: =C$5*B7 -> 226.47 | D7: =C7*D$3 -> 22.816852 | E7: =D7*28 -> 638.87187 | F7: =D7*30 -> 684.50558 | G7: =D7*31 -> 707.32243 | I7: 3 | J7: =J$5*I7 -> 241.8 | K7: =J7*K$3 -> 24.36135 | L7: =K7*28 -> 682.1178 | M7: =K7*30 -> 730.8405 | N7: =K7*31 -> 755.20185 | P7: 3 | Q7: =Q$5*P7 -> 253.47 | R7: =Q7*R$3 -> 25.537102 | S7: =R7*28 -> 715.03887 | T7: =R7*30 -> 766.11307 | U7: =R7*31 -> 791.65018 | W7: 3 | X7: =X$5*W7 -> 260.64 | Y7: =X7*Y$3 -> 26.25948 | Z7: =Y7*28 -> 735.26544 | AA7: =Y7*30 -> 787.7844 | AB7: =Y7*31 -> 814.04388 | AD7: 3 | AE7: =AE$5*AD7 -> 268.86 | AF7: =AE7*AF$3 -> 27.087645 | AG7: =AF7*28 -> 758.45406 | AH7: =AF7*30 -> 812.62935 | AI7: =AF7*31 -> 839.717 | AK7: 3 | AL7: =AL$5*AK7 -> 288.66 | AM7: =AL7*AM$3 -> 29.082495 | AN7: =AM7*28 -> 814.30986 | AO7: =AM7*30 -> 872.47485 | AP7: =AM7*31 -> 901.55734 | AR7: 3 | AS7: =AS$5*AR7 -> 311.22 | AT7: =AS7*AT$3 -> 34.750825 | AU7: =AT7*28 -> 973.02311 | AV7: =AT7*30 -> 1042.5248 | AW7: =AT7*31 -> 1077.2756 | AY7: 3 | AZ7: =AZ$5*AY7 -> 0 | BA7: =AZ7*BA$3 -> 0 | BB7: =BA7*28 -> 0 | BC7: =BA7*30 -> 0 | BD7: =BA7*31 -> 0 | BF7: 3 | BG7: =BG$5*BF7 -> 0 | BH7: =BG7*BH$3 -> 0 | BI7: =BH7*28 -> 0 | BJ7: =BH7*30 -> 0 | BK7: =BH7*31 -> 0 | BM7: 3 | BN7: =BN$5*BM7 -> 0 | BO7: =BN7*BO$3 -> 0 | BP7: =BO7*28 -> 0 | BQ7: =BO7*30 -> 0 | BR7: =BO7*31 -> 0 | BT7: 3 | BU7: =BU$5*BT7 -> 0 | BV7: =BU7*BV$3 -> 0 | BW7: =BV7*28 -> 0 | BX7: =BV7*30 -> 0 | BY7: =BV7*31 -> 0 | CA7: 3 | CB7: =CB$5*CA7 -> 0 | CC7: =CB7*CC$3 -> 0 | CD7: =CC7*28 -> 0 | CE7: =CC7*30 -> 0 | CF7: =CC7*31 -> 0 | CH7: 3 | CI7: =CI$5*CH7 -> 0 | CJ7: =CI7*CJ$3 -> 0 | CK7: =CJ7*28 -> 0 | CL7: =CJ7*30 -> 0 | CM7: =CJ7*31 -> 0 | CO7: 3 | CP7: =CP$5*CO7 -> 0 | CQ7: =CP7*CQ$3 -> 0 | CR7: =CQ7*28 -> 0 | CS7: =CQ7*30 -> 0 | CT7: =CQ7*31 -> 0 | CV7: 3 | CW7: =CW$5*CV7 -> 0 | CX7: =CW7*CX$3 -> 0 | CY7: =CX7*28 -> 0 | CZ7: =CX7*30 -> 0 | DA7: =CX7*31 -> 0 | DC7: 3 | DD7: =DD$5*DC7 -> 0 | DE7: =DD7*DE$3 -> 0 | DF7: =DE7*28 -> 0 | DG7: =DE7*30 -> 0 | DH7: =DE7*31 -> 0 | DJ7: 3 | DK7: =DK$5*DJ7 -> 0 | DL7: =DK7*DL$3 -> 0 | DM7: =DL7*28 -> 0 | DN7: =DL7*30 -> 0 | DO7: =DL7*31 -> 0 | DQ7: 3 | DR7: =DR$5*DQ7 -> 0 | DS7: =DR7*DS$3 -> 0 | DT7: =DS7*28 -> 0 | DU7: =DS7*30 -> 0 | DV7: =DS7*31 -> 0 | DX7: 3 | DY7: =DY$5*DX7 -> 0 | DZ7: =DY7*DZ$3 -> 0 | EA7: =DZ7*28 -> 0 | EB7: =DZ7*30 -> 0 | EC7: =DZ7*31 -> 0
B8: 4 | C8: =C$5*B8 -> 301.96 | D8: =C8*D$3 -> 30.42247 | E8: =D8*28 -> 851.82916 | F8: =D8*30 -> 912.6741 | G8: =D8*31 -> 943.09657 | I8: 4 | J8: =J$5*I8 -> 322.4 | K8: =J8*K$3 -> 32.4818 | L8: =K8*28 -> 909.4904 | M8: =K8*30 -> 974.454 | N8: =K8*31 -> 1006.9358 | P8: 4 | Q8: =Q$5*P8 -> 337.96 | R8: =Q8*R$3 -> 34.04947 | S8: =R8*28 -> 953.38516 | T8: =R8*30 -> 1021.4841 | U8: =R8*31 -> 1055.5336 | W8: 4 | X8: =X$5*W8 -> 347.52 | Y8: =X8*Y$3 -> 35.01264 | Z8: =Y8*28 -> 980.35392 | AA8: =Y8*30 -> 1050.3792 | AB8: =Y8*31 -> 1085.3918 | AD8: 4 | AE8: =AE$5*AD8 -> 358.48 | AF8: =AE8*AF$3 -> 36.11686 | AG8: =AF8*28 -> 1011.2721 | AH8: =AF8*30 -> 1083.5058 | AI8: =AF8*31 -> 1119.6227 | AK8: 4 | AL8: =AL$5*AK8 -> 384.88 | AM8: =AL8*AM$3 -> 38.77666 | AN8: =AM8*28 -> 1085.7465 | AO8: =AM8*30 -> 1163.2998 | AP8: =AM8*31 -> 1202.0765 | AR8: 4 | AS8: =AS$5*AR8 -> 414.96 | AT8: =AS8*AT$3 -> 46.334434 | AU8: =AT8*28 -> 1297.3641 | AV8: =AT8*30 -> 1390.033 | AW8: =AT8*31 -> 1436.3674 | AY8: 4 | AZ8: =AZ$5*AY8 -> 0 | BA8: =AZ8*BA$3 -> 0 | BB8: =BA8*28 -> 0 | BC8: =BA8*30 -> 0 | BD8: =BA8*31 -> 0 | BF8: 4 | BG8: =BG$5*BF8 -> 0 | BH8: =BG8*BH$3 -> 0 | BI8: =BH8*28 -> 0 | BJ8: =BH8*30 -> 0 | BK8: =BH8*31 -> 0 | BM8: 4 | BN8: =BN$5*BM8 -> 0 | BO8: =BN8*BO$3 -> 0 | BP8: =BO8*28 -> 0 | BQ8: =BO8*30 -> 0 | BR8: =BO8*31 -> 0 | BT8: 4 | BU8: =BU$5*BT8 -> 0 | BV8: =BU8*BV$3 -> 0 | BW8: =BV8*28 -> 0 | BX8: =BV8*30 -> 0 | BY8: =BV8*31 -> 0 | CA8: 4 | CB8: =CB$5*CA8 -> 0 | CC8: =CB8*CC$3 -> 0 | CD8: =CC8*28 -> 0 | CE8: =CC8*30 -> 0 | CF8: =CC8*31 -> 0 | CH8: 4 | CI8: =CI$5*CH8 -> 0 | CJ8: =CI8*CJ$3 -> 0 | CK8: =CJ8*28 -> 0 | CL8: =CJ8*30 -> 0 | CM8: =CJ8*31 -> 0 | CO8: 4 | CP8: =CP$5*CO8 -> 0 | CQ8: =CP8*CQ$3 -> 0 | CR8: =CQ8*28 -> 0 | CS8: =CQ8*30 -> 0 | CT8: =CQ8*31 -> 0 | CV8: 4 | CW8: =CW$5*CV8 -> 0 | CX8: =CW8*CX$3 -> 0 | CY8: =CX8*28 -> 0 | CZ8: =CX8*30 -> 0 | DA8: =CX8*31 -> 0 | DC8: 4 | DD8: =DD$5*DC8 -> 0 | DE8: =DD8*DE$3 -> 0 | DF8: =DE8*28 -> 0 | DG8: =DE8*30 -> 0 | DH8: =DE8*31 -> 0 | DJ8: 4 | DK8: =DK$5*DJ8 -> 0 | DL8: =DK8*DL$3 -> 0 | DM8: =DL8*28 -> 0 | DN8: =DL8*30 -> 0 | DO8: =DL8*31 -> 0 | DQ8: 4 | DR8: =DR$5*DQ8 -> 0 | DS8: =DR8*DS$3 -> 0 | DT8: =DS8*28 -> 0 | DU8: =DS8*30 -> 0 | DV8: =DS8*31 -> 0 | DX8: 4 | DY8: =DY$5*DX8 -> 0 | DZ8: =DY8*DZ$3 -> 0 | EA8: =DZ8*28 -> 0 | EB8: =DZ8*30 -> 0 | EC8: =DZ8*31 -> 0
B9: 5 | C9: =C$5*B9 -> 377.45 | D9: =C9*D$3 -> 38.028087 | E9: =D9*28 -> 1064.7865 | F9: =D9*30 -> 1140.8426 | G9: =D9*31 -> 1178.8707 | I9: 5 | J9: =J$5*I9 -> 403 | K9: =J9*K$3 -> 40.60225 | L9: =K9*28 -> 1136.863 | M9: =K9*30 -> 1218.0675 | N9: =K9*31 -> 1258.6698 | P9: 5 | Q9: =Q$5*P9 -> 422.45 | R9: =Q9*R$3 -> 42.561838 | S9: =R9*28 -> 1191.7314 | T9: =R9*30 -> 1276.8551 | U9: =R9*31 -> 1319.417 | W9: 5 | X9: =X$5*W9 -> 434.4 | Y9: =X9*Y$3 -> 43.7658 | Z9: =Y9*28 -> 1225.4424 | AA9: =Y9*30 -> 1312.974 | AB9: =Y9*31 -> 1356.7398 | AD9: 5 | AE9: =AE$5*AD9 -> 448.1 | AF9: =AE9*AF$3 -> 45.146075 | AG9: =AF9*28 -> 1264.0901 | AH9: =AF9*30 -> 1354.3823 | AI9: =AF9*31 -> 1399.5283 | AK9: 5 | AL9: =AL$5*AK9 -> 481.1 | AM9: =AL9*AM$3 -> 48.470825 | AN9: =AM9*28 -> 1357.1831 | AO9: =AM9*30 -> 1454.1248 | AP9: =AM9*31 -> 1502.5956 | AR9: 5 | AS9: =AS$5*AR9 -> 518.7 | AT9: =AS9*AT$3 -> 57.918042 | AU9: =AT9*28 -> 1621.7052 | AV9: =AT9*30 -> 1737.5413 | AW9: =AT9*31 -> 1795.4593 | AY9: 5 | AZ9: =AZ$5*AY9 -> 0 | BA9: =AZ9*BA$3 -> 0 | BB9: =BA9*28 -> 0 | BC9: =BA9*30 -> 0 | BD9: =BA9*31 -> 0 | BF9: 5 | BG9: =BG$5*BF9 -> 0 | BH9: =BG9*BH$3 -> 0 | BI9: =BH9*28 -> 0 | BJ9: =BH9*30 -> 0 | BK9: =BH9*31 -> 0 | BM9: 5 | BN9: =BN$5*BM9 -> 0 | BO9: =BN9*BO$3 -> 0 | BP9: =BO9*28 -> 0 | BQ9: =BO9*30 -> 0 | BR9: =BO9*31 -> 0 | BT9: 5 | BU9: =BU$5*BT9 -> 0 | BV9: =BU9*BV$3 -> 0 | BW9: =BV9*28 -> 0 | BX9: =BV9*30 -> 0 | BY9: =BV9*31 -> 0 | CA9: 5 | CB9: =CB$5*CA9 -> 0 | CC9: =CB9*CC$3 -> 0 | CD9: =CC9*28 -> 0 | CE9: =CC9*30 -> 0 | CF9: =CC9*31 -> 0 | CH9: 5 | CI9: =CI$5*CH9 -> 0 | CJ9: =CI9*CJ$3 -> 0 | CK9: =CJ9*28 -> 0 | CL9: =CJ9*30 -> 0 | CM9: =CJ9*31 -> 0 | CO9: 5 | CP9: =CP$5*CO9 -> 0 | CQ9: =CP9*CQ$3 -> 0 | CR9: =CQ9*28 -> 0 | CS9: =CQ9*30 -> 0 | CT9: =CQ9*31 -> 0 | CV9: 5 | CW9: =CW$5*CV9 -> 0 | CX9: =CW9*CX$3 -> 0 | CY9: =CX9*28 -> 0 | CZ9: =CX9*30 -> 0 | DA9: =CX9*31 -> 0 | DC9: 5 | DD9: =DD$5*DC9 -> 0 | DE9: =DD9*DE$3 -> 0 | DF9: =DE9*28 -> 0 | DG9: =DE9*30 -> 0 | DH9: =DE9*31 -> 0 | DJ9: 5 | DK9: =DK$5*DJ9 -> 0 | DL9: =DK9*DL$3 -> 0 | DM9: =DL9*28 -> 0 | DN9: =DL9*30 -> 0 | DO9: =DL9*31 -> 0 | DQ9: 5 | DR9: =DR$5*DQ9 -> 0 | DS9: =DR9*DS$3 -> 0 | DT9: =DS9*28 -> 0 | DU9: =DS9*30 -> 0 | DV9: =DS9*31 -> 0 | DX9: 5 | DY9: =DY$5*DX9 -> 0 | DZ9: =DY9*DZ$3 -> 0 | EA9: =DZ9*28 -> 0 | EB9: =DZ9*30 -> 0 | EC9: =DZ9*31 -> 0
B10: 6 | C10: =C$5*B10 -> 452.94 | D10: =C10*D$3 -> 45.633705 | E10: =D10*28 -> 1277.7437 | F10: =D10*30 -> 1369.0112 | G10: =D10*31 -> 1414.6449 | I10: 6 | J10: =J$5*I10 -> 483.6 | K10: =J10*K$3 -> 48.7227 | L10: =K10*28 -> 1364.2356 | M10: =K10*30 -> 1461.681 | N10: =K10*31 -> 1510.4037 | P10: 6 | Q10: =Q$5*P10 -> 506.94 | R10: =Q10*R$3 -> 51.074205 | S10: =R10*28 -> 1430.0777 | T10: =R10*30 -> 1532.2261 | U10: =R10*31 -> 1583.3004 | W10: 6 | X10: =X$5*W10 -> 521.28 | Y10: =X10*Y$3 -> 52.51896 | Z10: =Y10*28 -> 1470.5309 | AA10: =Y10*30 -> 1575.5688 | AB10: =Y10*31 -> 1628.0878 | AD10: 6 | AE10: =AE$5*AD10 -> 537.72 | AF10: =AE10*AF$3 -> 54.17529 | AG10: =AF10*28 -> 1516.9081 | AH10: =AF10*30 -> 1625.2587 | AI10: =AF10*31 -> 1679.434 | AK10: 6 | AL10: =AL$5*AK10 -> 577.32 | AM10: =AL10*AM$3 -> 58.16499 | AN10: =AM10*28 -> 1628.6197 | AO10: =AM10*30 -> 1744.9497 | AP10: =AM10*31 -> 1803.1147 | AR10: 6 | AS10: =AS$5*AR10 -> 622.44 | AT10: =AS10*AT$3 -> 69.50165 | AU10: =AT10*28 -> 1946.0462 | AV10: =AT10*30 -> 2085.0495 | AW10: =AT10*31 -> 2154.5512 | AY10: 6 | AZ10: =AZ$5*AY10 -> 0 | BA10: =AZ10*BA$3 -> 0 | BB10: =BA10*28 -> 0 | BC10: =BA10*30 -> 0 | BD10: =BA10*31 -> 0 | BF10: 6 | BG10: =BG$5*BF10 -> 0 | BH10: =BG10*BH$3 -> 0 | BI10: =BH10*28 -> 0 | BJ10: =BH10*30 -> 0 | BK10: =BH10*31 -> 0 | BM10: 6 | BN10: =BN$5*BM10 -> 0 | BO10: =BN10*BO$3 -> 0 | BP10: =BO10*28 -> 0 | BQ10: =BO10*30 -> 0 | BR10: =BO10*31 -> 0 | BT10: 6 | BU10: =BU$5*BT10 -> 0 | BV10: =BU10*BV$3 -> 0 | BW10: =BV10*28 -> 0 | BX10: =BV10*30 -> 0 | BY10: =BV10*31 -> 0 | CA10: 6 | CB10: =CB$5*CA10 -> 0 | CC10: =CB10*CC$3 -> 0 | CD10: =CC10*28 -> 0 | CE10: =CC10*30 -> 0 | CF10: =CC10*31 -> 0 | CH10: 6 | CI10: =CI$5*CH10 -> 0 | CJ10: =CI10*CJ$3 -> 0 | CK10: =CJ10*28 -> 0 | CL10: =CJ10*30 -> 0 | CM10: =CJ10*31 -> 0 | CO10: 6 | CP10: =CP$5*CO10 -> 0 | CQ10: =CP10*CQ$3 -> 0 | CR10: =CQ10*28 -> 0 | CS10: =CQ10*30 -> 0 | CT10: =CQ10*31 -> 0 | CV10: 6 | CW10: =CW$5*CV10 -> 0 | CX10: =CW10*CX$3 -> 0 | CY10: =CX10*28 -> 0 | CZ10: =CX10*30 -> 0 | DA10: =CX10*31 -> 0 | DC10: 6 | DD10: =DD$5*DC10 -> 0 | DE10: =DD10*DE$3 -> 0 | DF10: =DE10*28 -> 0 | DG10: =DE10*30 -> 0 | DH10: =DE10*31 -> 0 | DJ10: 6 | DK10: =DK$5*DJ10 -> 0 | DL10: =DK10*DL$3 -> 0 | DM10: =DL10*28 -> 0 | DN10: =DL10*30 -> 0 | DO10: =DL10*31 -> 0 | DQ10: 6 | DR10: =DR$5*DQ10 -> 0 | DS10: =DR10*DS$3 -> 0 | DT10: =DS10*28 -> 0 | DU10: =DS10*30 -> 0 | DV10: =DS10*31 -> 0 | DX10: 6 | DY10: =DY$5*DX10 -> 0 | DZ10: =DY10*DZ$3 -> 0 | EA10: =DZ10*28 -> 0 | EB10: =DZ10*30 -> 0 | EC10: =DZ10*31 -> 0
B11: 7 | C11: =C$5*B11 -> 528.43 | D11: =C11*D$3 -> 53.239323 | E11: =D11*28 -> 1490.701 | F11: =D11*30 -> 1597.1797 | G11: =D11*31 -> 1650.419 | I11: 7 | J11: =J$5*I11 -> 564.2 | K11: =J11*K$3 -> 56.84315 | L11: =K11*28 -> 1591.6082 | M11: =K11*30 -> 1705.2945 | N11: =K11*31 -> 1762.1376 | P11: 7 | Q11: =Q$5*P11 -> 591.43 | R11: =Q11*R$3 -> 59.586572 | S11: =R11*28 -> 1668.424 | T11: =R11*30 -> 1787.5972 | U11: =R11*31 -> 1847.1837 | W11: 7 | X11: =X$5*W11 -> 608.16 | Y11: =X11*Y$3 -> 61.27212 | Z11: =Y11*28 -> 1715.6194 | AA11: =Y11*30 -> 1838.1636 | AB11: =Y11*31 -> 1899.4357 | AD11: 7 | AE11: =AE$5*AD11 -> 627.34 | AF11: =AE11*AF$3 -> 63.204505 | AG11: =AF11*28 -> 1769.7261 | AH11: =AF11*30 -> 1896.1352 | AI11: =AF11*31 -> 1959.3397 | AK11: 7 | AL11: =AL$5*AK11 -> 673.54 | AM11: =AL11*AM$3 -> 67.859155 | AN11: =AM11*28 -> 1900.0563 | AO11: =AM11*30 -> 2035.7747 | AP11: =AM11*31 -> 2103.6338 | AR11: 7 | AS11: =AS$5*AR11 -> 726.18 | AT11: =AS11*AT$3 -> 81.085259 | AU11: =AT11*28 -> 2270.3872 | AV11: =AT11*30 -> 2432.5578 | AW11: =AT11*31 -> 2513.643 | AY11: 7 | AZ11: =AZ$5*AY11 -> 0 | BA11: =AZ11*BA$3 -> 0 | BB11: =BA11*28 -> 0 | BC11: =BA11*30 -> 0 | BD11: =BA11*31 -> 0 | BF11: 7 | BG11: =BG$5*BF11 -> 0 | BH11: =BG11*BH$3 -> 0 | BI11: =BH11*28 -> 0 | BJ11: =BH11*30 -> 0 | BK11: =BH11*31 -> 0 | BM11: 7 | BN11: =BN$5*BM11 -> 0 | BO11: =BN11*BO$3 -> 0 | BP11: =BO11*28 -> 0 | BQ11: =BO11*30 -> 0 | BR11: =BO11*31 -> 0 | BT11: 7 | BU11: =BU$5*BT11 -> 0 | BV11: =BU11*BV$3 -> 0 | BW11: =BV11*28 -> 0 | BX11: =BV11*30 -> 0 | BY11: =BV11*31 -> 0 | CA11: 7 | CB11: =CB$5*CA11 -> 0 | CC11: =CB11*CC$3 -> 0 | CD11: =CC11*28 -> 0 | CE11: =CC11*30 -> 0 | CF11: =CC11*31 -> 0 | CH11: 7 | CI11: =CI$5*CH11 -> 0 | CJ11: =CI11*CJ$3 -> 0 | CK11: =CJ11*28 -> 0 | CL11: =CJ11*30 -> 0 | CM11: =CJ11*31 -> 0 | CO11: 7 | CP11: =CP$5*CO11 -> 0 | CQ11: =CP11*CQ$3 -> 0 | CR11: =CQ11*28 -> 0 | CS11: =CQ11*30 -> 0 | CT11: =CQ11*31 -> 0 | CV11: 7 | CW11: =CW$5*CV11 -> 0 | CX11: =CW11*CX$3 -> 0 | CY11: =CX11*28 -> 0 | CZ11: =CX11*30 -> 0 | DA11: =CX11*31 -> 0 | DC11: 7 | DD11: =DD$5*DC11 -> 0 | DE11: =DD11*DE$3 -> 0 | DF11: =DE11*28 -> 0 | DG11: =DE11*30 -> 0 | DH11: =DE11*31 -> 0 | DJ11: 7 | DK11: =DK$5*DJ11 -> 0 | DL11: =DK11*DL$3 -> 0 | DM11: =DL11*28 -> 0 | DN11: =DL11*30 -> 0 | DO11: =DL11*31 -> 0 | DQ11: 7 | DR11: =DR$5*DQ11 -> 0 | DS11: =DR11*DS$3 -> 0 | DT11: =DS11*28 -> 0 | DU11: =DS11*30 -> 0 | DV11: =DS11*31 -> 0 | DX11: 7 | DY11: =DY$5*DX11 -> 0 | DZ11: =DY11*DZ$3 -> 0 | EA11: =DZ11*28 -> 0 | EB11: =DZ11*30 -> 0 | EC11: =DZ11*31 -> 0
B12: 8 | C12: =C$5*B12 -> 603.92 | D12: =C12*D$3 -> 60.84494 | E12: =D12*28 -> 1703.6583 | F12: =D12*30 -> 1825.3482 | G12: =D12*31 -> 1886.1931 | I12: 8 | J12: =J$5*I12 -> 644.8 | K12: =J12*K$3 -> 64.9636 | L12: =K12*28 -> 1818.9808 | M12: =K12*30 -> 1948.908 | N12: =K12*31 -> 2013.8716 | P12: 8 | Q12: =Q$5*P12 -> 675.92 | R12: =Q12*R$3 -> 68.09894 | S12: =R12*28 -> 1906.7703 | T12: =R12*30 -> 2042.9682 | U12: =R12*31 -> 2111.0671 | W12: 8 | X12: =X$5*W12 -> 695.04 | Y12: =X12*Y$3 -> 70.02528 | Z12: =Y12*28 -> 1960.7078 | AA12: =Y12*30 -> 2100.7584 | AB12: =Y12*31 -> 2170.7837 | AD12: 8 | AE12: =AE$5*AD12 -> 716.96 | AF12: =AE12*AF$3 -> 72.23372 | AG12: =AF12*28 -> 2022.5442 | AH12: =AF12*30 -> 2167.0116 | AI12: =AF12*31 -> 2239.2453 | AK12: 8 | AL12: =AL$5*AK12 -> 769.76 | AM12: =AL12*AM$3 -> 77.55332 | AN12: =AM12*28 -> 2171.493 | AO12: =AM12*30 -> 2326.5996 | AP12: =AM12*31 -> 2404.1529 | AR12: 8 | AS12: =AS$5*AR12 -> 829.92 | AT12: =AS12*AT$3 -> 92.668867 | AU12: =AT12*28 -> 2594.7283 | AV12: =AT12*30 -> 2780.066 | AW12: =AT12*31 -> 2872.7349 | AY12: 8 | AZ12: =AZ$5*AY12 -> 0 | BA12: =AZ12*BA$3 -> 0 | BB12: =BA12*28 -> 0 | BC12: =BA12*30 -> 0 | BD12: =BA12*31 -> 0 | BF12: 8 | BG12: =BG$5*BF12 -> 0 | BH12: =BG12*BH$3 -> 0 | BI12: =BH12*28 -> 0 | BJ12: =BH12*30 -> 0 | BK12: =BH12*31 -> 0 | BM12: 8 | BN12: =BN$5*BM12 -> 0 | BO12: =BN12*BO$3 -> 0 | BP12: =BO12*28 -> 0 | BQ12: =BO12*30 -> 0 | BR12: =BO12*31 -> 0 | BT12: 8 | BU12: =BU$5*BT12 -> 0 | BV12: =BU12*BV$3 -> 0 | BW12: =BV12*28 -> 0 | BX12: =BV12*30 -> 0 | BY12: =BV12*31 -> 0 | CA12: 8 | CB12: =CB$5*CA12 -> 0 | CC12: =CB12*CC$3 -> 0 | CD12: =CC12*28 -> 0 | CE12: =CC12*30 -> 0 | CF12: =CC12*31 -> 0 | CH12: 8 | CI12: =CI$5*CH12 -> 0 | CJ12: =CI12*CJ$3 -> 0 | CK12: =CJ12*28 -> 0 | CL12: =CJ12*30 -> 0 | CM12: =CJ12*31 -> 0 | CO12: 8 | CP12: =CP$5*CO12 -> 0 | CQ12: =CP12*CQ$3 -> 0 | CR12: =CQ12*28 -> 0 | CS12: =CQ12*30 -> 0 | CT12: =CQ12*31 -> 0 | CV12: 8 | CW12: =CW$5*CV12 -> 0 | CX12: =CW12*CX$3 -> 0 | CY12: =CX12*28 -> 0 | CZ12: =CX12*30 -> 0 | DA12: =CX12*31 -> 0 | DC12: 8 | DD12: =DD$5*DC12 -> 0 | DE12: =DD12*DE$3 -> 0 | DF12: =DE12*28 -> 0 | DG12: =DE12*30 -> 0 | DH12: =DE12*31 -> 0 | DJ12: 8 | DK12: =DK$5*DJ12 -> 0 | DL12: =DK12*DL$3 -> 0 | DM12: =DL12*28 -> 0 | DN12: =DL12*30 -> 0 | DO12: =DL12*31 -> 0 | DQ12: 8 | DR12: =DR$5*DQ12 -> 0 | DS12: =DR12*DS$3 -> 0 | DT12: =DS12*28 -> 0 | DU12: =DS12*30 -> 0 | DV12: =DS12*31 -> 0 | DX12: 8 | DY12: =DY$5*DX12 -> 0 | DZ12: =DY12*DZ$3 -> 0 | EA12: =DZ12*28 -> 0 | EB12: =DZ12*30 -> 0 | EC12: =DZ12*31 -> 0
B13: 9 | C13: =C$5*B13 -> 679.41 | D13: =C13*D$3 -> 68.450558 | E13: =D13*28 -> 1916.6156 | F13: =D13*30 -> 2053.5167 | G13: =D13*31 -> 2121.9673 | I13: 9 | J13: =J$5*I13 -> 725.4 | K13: =J13*K$3 -> 73.08405 | L13: =K13*28 -> 2046.3534 | M13: =K13*30 -> 2192.5215 | N13: =K13*31 -> 2265.6056 | P13: 9 | Q13: =Q$5*P13 -> 760.41 | R13: =Q13*R$3 -> 76.611307 | S13: =R13*28 -> 2145.1166 | T13: =R13*30 -> 2298.3392 | U13: =R13*31 -> 2374.9505 | W13: 9 | X13: =X$5*W13 -> 781.92 | Y13: =X13*Y$3 -> 78.77844 | Z13: =Y13*28 -> 2205.7963 | AA13: =Y13*30 -> 2363.3532 | AB13: =Y13*31 -> 2442.1316 | AD13: 9 | AE13: =AE$5*AD13 -> 806.58 | AF13: =AE13*AF$3 -> 81.262935 | AG13: =AF13*28 -> 2275.3622 | AH13: =AF13*30 -> 2437.8881 | AI13: =AF13*31 -> 2519.151 | AK13: 9 | AL13: =AL$5*AK13 -> 865.98 | AM13: =AL13*AM$3 -> 87.247485 | AN13: =AM13*28 -> 2442.9296 | AO13: =AM13*30 -> 2617.4246 | AP13: =AM13*31 -> 2704.672 | AR13: 9 | AS13: =AS$5*AR13 -> 933.66 | AT13: =AS13*AT$3 -> 104.25248 | AU13: =AT13*28 -> 2919.0693 | AV13: =AT13*30 -> 3127.5743 | AW13: =AT13*31 -> 3231.8267 | AY13: 9 | AZ13: =AZ$5*AY13 -> 0 | BA13: =AZ13*BA$3 -> 0 | BB13: =BA13*28 -> 0 | BC13: =BA13*30 -> 0 | BD13: =BA13*31 -> 0 | BF13: 9 | BG13: =BG$5*BF13 -> 0 | BH13: =BG13*BH$3 -> 0 | BI13: =BH13*28 -> 0 | BJ13: =BH13*30 -> 0 | BK13: =BH13*31 -> 0 | BM13: 9 | BN13: =BN$5*BM13 -> 0 | BO13: =BN13*BO$3 -> 0 | BP13: =BO13*28 -> 0 | BQ13: =BO13*30 -> 0 | BR13: =BO13*31 -> 0 | BT13: 9 | BU13: =BU$5*BT13 -> 0 | BV13: =BU13*BV$3 -> 0 | BW13: =BV13*28 -> 0 | BX13: =BV13*30 -> 0 | BY13: =BV13*31 -> 0 | CA13: 9 | CB13: =CB$5*CA13 -> 0 | CC13: =CB13*CC$3 -> 0 | CD13: =CC13*28 -> 0 | CE13: =CC13*30 -> 0 | CF13: =CC13*31 -> 0 | CH13: 9 | CI13: =CI$5*CH13 -> 0 | CJ13: =CI13*CJ$3 -> 0 | CK13: =CJ13*28 -> 0 | CL13: =CJ13*30 -> 0 | CM13: =CJ13*31 -> 0 | CO13: 9 | CP13: =CP$5*CO13 -> 0 | CQ13: =CP13*CQ$3 -> 0 | CR13: =CQ13*28 -> 0 | CS13: =CQ13*30 -> 0 | CT13: =CQ13*31 -> 0 | CV13: 9 | CW13: =CW$5*CV13 -> 0 | CX13: =CW13*CX$3 -> 0 | CY13: =CX13*28 -> 0 | CZ13: =CX13*30 -> 0 | DA13: =CX13*31 -> 0 | DC13: 9 | DD13: =DD$5*DC13 -> 0 | DE13: =DD13*DE$3 -> 0 | DF13: =DE13*28 -> 0 | DG13: =DE13*30 -> 0 | DH13: =DE13*31 -> 0 | DJ13: 9 | DK13: =DK$5*DJ13 -> 0 | DL13: =DK13*DL$3 -> 0 | DM13: =DL13*28 -> 0 | DN13: =DL13*30 -> 0 | DO13: =DL13*31 -> 0 | DQ13: 9 | DR13: =DR$5*DQ13 -> 0 | DS13: =DR13*DS$3 -> 0 | DT13: =DS13*28 -> 0 | DU13: =DS13*30 -> 0 | DV13: =DS13*31 -> 0 | DX13: 9 | DY13: =DY$5*DX13 -> 0 | DZ13: =DY13*DZ$3 -> 0 | EA13: =DZ13*28 -> 0 | EB13: =DZ13*30 -> 0 | EC13: =DZ13*31 -> 0
B14: 10 | C14: =C$5*B14 -> 754.9 | D14: =C14*D$3 -> 76.056175 | E14: =D14*28 -> 2129.5729 | F14: =D14*30 -> 2281.6852 | G14: =D14*31 -> 2357.7414 | I14: 10 | J14: =J$5*I14 -> 806 | K14: =J14*K$3 -> 81.2045 | L14: =K14*28 -> 2273.726 | M14: =K14*30 -> 2436.135 | N14: =K14*31 -> 2517.3395 | P14: 10 | Q14: =Q$5*P14 -> 844.9 | R14: =Q14*R$3 -> 85.123675 | S14: =R14*28 -> 2383.4629 | T14: =R14*30 -> 2553.7103 | U14: =R14*31 -> 2638.8339 | W14: 10 | X14: =X$5*W14 -> 868.8 | Y14: =X14*Y$3 -> 87.5316 | Z14: =Y14*28 -> 2450.8848 | AA14: =Y14*30 -> 2625.948 | AB14: =Y14*31 -> 2713.4796 | AD14: 10 | AE14: =AE$5*AD14 -> 896.2 | AF14: =AE14*AF$3 -> 90.29215 | AG14: =AF14*28 -> 2528.1802 | AH14: =AF14*30 -> 2708.7645 | AI14: =AF14*31 -> 2799.0566 | AK14: 10 | AL14: =AL$5*AK14 -> 962.2 | AM14: =AL14*AM$3 -> 96.94165 | AN14: =AM14*28 -> 2714.3662 | AO14: =AM14*30 -> 2908.2495 | AP14: =AM14*31 -> 3005.1912 | AR14: 10 | AS14: =AS$5*AR14 -> 1037.4 | AT14: =AS14*AT$3 -> 115.83608 | AU14: =AT14*28 -> 3243.4104 | AV14: =AT14*30 -> 3475.0825 | AW14: =AT14*31 -> 3590.9186 | AY14: 10 | AZ14: =AZ$5*AY14 -> 0 | BA14: =AZ14*BA$3 -> 0 | BB14: =BA14*28 -> 0 | BC14: =BA14*30 -> 0 | BD14: =BA14*31 -> 0 | BF14: 10 | BG14: =BG$5*BF14 -> 0 | BH14: =BG14*BH$3 -> 0 | BI14: =BH14*28 -> 0 | BJ14: =BH14*30 -> 0 | BK14: =BH14*31 -> 0 | BM14: 10 | BN14: =BN$5*BM14 -> 0 | BO14: =BN14*BO$3 -> 0 | BP14: =BO14*28 -> 0 | BQ14: =BO14*30 -> 0 | BR14: =BO14*31 -> 0 | BT14: 10 | BU14: =BU$5*BT14 -> 0 | BV14: =BU14*BV$3 -> 0 | BW14: =BV14*28 -> 0 | BX14: =BV14*30 -> 0 | BY14: =BV14*31 -> 0 | CA14: 10 | CB14: =CB$5*CA14 -> 0 | CC14: =CB14*CC$3 -> 0 | CD14: =CC14*28 -> 0 | CE14: =CC14*30 -> 0 | CF14: =CC14*31 -> 0 | CH14: 10 | CI14: =CI$5*CH14 -> 0 | CJ14: =CI14*CJ$3 -> 0 | CK14: =CJ14*28 -> 0 | CL14: =CJ14*30 -> 0 | CM14: =CJ14*31 -> 0 | CO14: 10 | CP14: =CP$5*CO14 -> 0 | CQ14: =CP14*CQ$3 -> 0 | CR14: =CQ14*28 -> 0 | CS14: =CQ14*30 -> 0 | CT14: =CQ14*31 -> 0 | CV14: 10 | CW14: =CW$5*CV14 -> 0 | CX14: =CW14*CX$3 -> 0 | CY14: =CX14*28 -> 0 | CZ14: =CX14*30 -> 0 | DA14: =CX14*31 -> 0 | DC14: 10 | DD14: =DD$5*DC14 -> 0 | DE14: =DD14*DE$3 -> 0 | DF14: =DE14*28 -> 0 | DG14: =DE14*30 -> 0 | DH14: =DE14*31 -> 0 | DJ14: 10 | DK14: =DK$5*DJ14 -> 0 | DL14: =DK14*DL$3 -> 0 | DM14: =DL14*28 -> 0 | DN14: =DL14*30 -> 0 | DO14: =DL14*31 -> 0 | DQ14: 10 | DR14: =DR$5*DQ14 -> 0 | DS14: =DR14*DS$3 -> 0 | DT14: =DS14*28 -> 0 | DU14: =DS14*30 -> 0 | DV14: =DS14*31 -> 0 | DX14: 10 | DY14: =DY$5*DX14 -> 0 | DZ14: =DY14*DZ$3 -> 0 | EA14: =DZ14*28 -> 0 | EB14: =DZ14*30 -> 0 | EC14: =DZ14*31 -> 0
B15: 11 | C15: =C$5*B15 -> 830.39 | D15: =C15*D$3 -> 83.661793 | E15: =D15*28 -> 2342.5302 | F15: =D15*30 -> 2509.8538 | G15: =D15*31 -> 2593.5156 | I15: 11 | J15: =J$5*I15 -> 886.6 | K15: =J15*K$3 -> 89.32495 | L15: =K15*28 -> 2501.0986 | M15: =K15*30 -> 2679.7485 | N15: =K15*31 -> 2769.0734 | P15: 11 | Q15: =Q$5*P15 -> 929.39 | R15: =Q15*R$3 -> 93.636043 | S15: =R15*28 -> 2621.8092 | T15: =R15*30 -> 2809.0813 | U15: =R15*31 -> 2902.7173 | W15: 11 | X15: =X$5*W15 -> 955.68 | Y15: =X15*Y$3 -> 96.28476 | Z15: =Y15*28 -> 2695.9733 | AA15: =Y15*30 -> 2888.5428 | AB15: =Y15*31 -> 2984.8276 | AD15: 11 | AE15: =AE$5*AD15 -> 985.82 | AF15: =AE15*AF$3 -> 99.321365 | AG15: =AF15*28 -> 2780.9982 | AH15: =AF15*30 -> 2979.641 | AI15: =AF15*31 -> 3078.9623 | AK15: 11 | AL15: =AL$5*AK15 -> 1058.42 | AM15: =AL15*AM$3 -> 106.63582 | AN15: =AM15*28 -> 2985.8028 | AO15: =AM15*30 -> 3199.0745 | AP15: =AM15*31 -> 3305.7103 | AR15: 11 | AS15: =AS$5*AR15 -> 1141.14 | AT15: =AS15*AT$3 -> 127.41969 | AU15: =AT15*28 -> 3567.7514 | AV15: =AT15*30 -> 3822.5908 | AW15: =AT15*31 -> 3950.0105 | AY15: 11 | AZ15: =AZ$5*AY15 -> 0 | BA15: =AZ15*BA$3 -> 0 | BB15: =BA15*28 -> 0 | BC15: =BA15*30 -> 0 | BD15: =BA15*31 -> 0 | BF15: 11 | BG15: =BG$5*BF15 -> 0 | BH15: =BG15*BH$3 -> 0 | BI15: =BH15*28 -> 0 | BJ15: =BH15*30 -> 0 | BK15: =BH15*31 -> 0 | BM15: 11 | BN15: =BN$5*BM15 -> 0 | BO15: =BN15*BO$3 -> 0 | BP15: =BO15*28 -> 0 | BQ15: =BO15*30 -> 0 | BR15: =BO15*31 -> 0 | BT15: 11 | BU15: =BU$5*BT15 -> 0 | BV15: =BU15*BV$3 -> 0 | BW15: =BV15*28 -> 0 | BX15: =BV15*30 -> 0 | BY15: =BV15*31 -> 0 | CA15: 11 | CB15: =CB$5*CA15 -> 0 | CC15: =CB15*CC$3 -> 0 | CD15: =CC15*28 -> 0 | CE15: =CC15*30 -> 0 | CF15: =CC15*31 -> 0 | CH15: 11 | CI15: =CI$5*CH15 -> 0 | CJ15: =CI15*CJ$3 -> 0 | CK15: =CJ15*28 -> 0 | CL15: =CJ15*30 -> 0 | CM15: =CJ15*31 -> 0 | CO15: 11 | CP15: =CP$5*CO15 -> 0 | CQ15: =CP15*CQ$3 -> 0 | CR15: =CQ15*28 -> 0 | CS15: =CQ15*30 -> 0 | CT15: =CQ15*31 -> 0 | CV15: 11 | CW15: =CW$5*CV15 -> 0 | CX15: =CW15*CX$3 -> 0 | CY15: =CX15*28 -> 0 | CZ15: =CX15*30 -> 0 | DA15: =CX15*31 -> 0 | DC15: 11 | DD15: =DD$5*DC15 -> 0 | DE15: =DD15*DE$3 -> 0 | DF15: =DE15*28 -> 0 | DG15: =DE15*30 -> 0 | DH15: =DE15*31 -> 0 | DJ15: 11 | DK15: =DK$5*DJ15 -> 0 | DL15: =DK15*DL$3 -> 0 | DM15: =DL15*28 -> 0 | DN15: =DL15*30 -> 0 | DO15: =DL15*31 -> 0 | DQ15: 11 | DR15: =DR$5*DQ15 -> 0 | DS15: =DR15*DS$3 -> 0 | DT15: =DS15*28 -> 0 | DU15: =DS15*30 -> 0 | DV15: =DS15*31 -> 0 | DX15: 11 | DY15: =DY$5*DX15 -> 0 | DZ15: =DY15*DZ$3 -> 0 | EA15: =DZ15*28 -> 0 | EB15: =DZ15*30 -> 0 | EC15: =DZ15*31 -> 0
B16: 12 | C16: =C$5*B16 -> 905.88 | D16: =C16*D$3 -> 91.26741 | E16: =D16*28 -> 2555.4875 | F16: =D16*30 -> 2738.0223 | G16: =D16*31 -> 2829.2897 | I16: 12 | J16: =J$5*I16 -> 967.2 | K16: =J16*K$3 -> 97.4454 | L16: =K16*28 -> 2728.4712 | M16: =K16*30 -> 2923.362 | N16: =K16*31 -> 3020.8074 | P16: 12 | Q16: =Q$5*P16 -> 1013.88 | R16: =Q16*R$3 -> 102.14841 | S16: =R16*28 -> 2860.1555 | T16: =R16*30 -> 3064.4523 | U16: =R16*31 -> 3166.6007 | W16: 12 | X16: =X$5*W16 -> 1042.56 | Y16: =X16*Y$3 -> 105.03792 | Z16: =Y16*28 -> 2941.0618 | AA16: =Y16*30 -> 3151.1376 | AB16: =Y16*31 -> 3256.1755 | AD16: 12 | AE16: =AE$5*AD16 -> 1075.44 | AF16: =AE16*AF$3 -> 108.35058 | AG16: =AF16*28 -> 3033.8162 | AH16: =AF16*30 -> 3250.5174 | AI16: =AF16*31 -> 3358.868 | AK16: 12 | AL16: =AL$5*AK16 -> 1154.64 | AM16: =AL16*AM$3 -> 116.32998 | AN16: =AM16*28 -> 3257.2394 | AO16: =AM16*30 -> 3489.8994 | AP16: =AM16*31 -> 3606.2294 | AR16: 12 | AS16: =AS$5*AR16 -> 1244.88 | AT16: =AS16*AT$3 -> 139.0033 | AU16: =AT16*28 -> 3892.0924 | AV16: =AT16*30 -> 4170.099 | AW16: =AT16*31 -> 4309.1023 | AY16: 12 | AZ16: =AZ$5*AY16 -> 0 | BA16: =AZ16*BA$3 -> 0 | BB16: =BA16*28 -> 0 | BC16: =BA16*30 -> 0 | BD16: =BA16*31 -> 0 | BF16: 12 | BG16: =BG$5*BF16 -> 0 | BH16: =BG16*BH$3 -> 0 | BI16: =BH16*28 -> 0 | BJ16: =BH16*30 -> 0 | BK16: =BH16*31 -> 0 | BM16: 12 | BN16: =BN$5*BM16 -> 0 | BO16: =BN16*BO$3 -> 0 | BP16: =BO16*28 -> 0 | BQ16: =BO16*30 -> 0 | BR16: =BO16*31 -> 0 | BT16: 12 | BU16: =BU$5*BT16 -> 0 | BV16: =BU16*BV$3 -> 0 | BW16: =BV16*28 -> 0 | BX16: =BV16*30 -> 0 | BY16: =BV16*31 -> 0 | CA16: 12 | CB16: =CB$5*CA16 -> 0 | CC16: =CB16*CC$3 -> 0 | CD16: =CC16*28 -> 0 | CE16: =CC16*30 -> 0 | CF16: =CC16*31 -> 0 | CH16: 12 | CI16: =CI$5*CH16 -> 0 | CJ16: =CI16*CJ$3 -> 0 | CK16: =CJ16*28 -> 0 | CL16: =CJ16*30 -> 0 | CM16: =CJ16*31 -> 0 | CO16: 12 | CP16: =CP$5*CO16 -> 0 | CQ16: =CP16*CQ$3 -> 0 | CR16: =CQ16*28 -> 0 | CS16: =CQ16*30 -> 0 | CT16: =CQ16*31 -> 0 | CV16: 12 | CW16: =CW$5*CV16 -> 0 | CX16: =CW16*CX$3 -> 0 | CY16: =CX16*28 -> 0 | CZ16: =CX16*30 -> 0 | DA16: =CX16*31 -> 0 | DC16: 12 | DD16: =DD$5*DC16 -> 0 | DE16: =DD16*DE$3 -> 0 | DF16: =DE16*28 -> 0 | DG16: =DE16*30 -> 0 | DH16: =DE16*31 -> 0 | DJ16: 12 | DK16: =DK$5*DJ16 -> 0 | DL16: =DK16*DL$3 -> 0 | DM16: =DL16*28 -> 0 | DN16: =DL16*30 -> 0 | DO16: =DL16*31 -> 0 | DQ16: 12 | DR16: =DR$5*DQ16 -> 0 | DS16: =DR16*DS$3 -> 0 | DT16: =DS16*28 -> 0 | DU16: =DS16*30 -> 0 | DV16: =DS16*31 -> 0 | DX16: 12 | DY16: =DY$5*DX16 -> 0 | DZ16: =DY16*DZ$3 -> 0 | EA16: =DZ16*28 -> 0 | EB16: =DZ16*30 -> 0 | EC16: =DZ16*31 -> 0
B17: 13 | C17: =C$5*B17 -> 981.37 | D17: =C17*D$3 -> 98.873027 | E17: =D17*28 -> 2768.4448 | F17: =D17*30 -> 2966.1908 | G17: =D17*31 -> 3065.0639 | I17: 13 | J17: =J$5*I17 -> 1047.8 | K17: =J17*K$3 -> 105.56585 | L17: =K17*28 -> 2955.8438 | M17: =K17*30 -> 3166.9755 | N17: =K17*31 -> 3272.5413 | P17: 13 | Q17: =Q$5*P17 -> 1098.37 | R17: =Q17*R$3 -> 110.66078 | S17: =R17*28 -> 3098.5018 | T17: =R17*30 -> 3319.8233 | U17: =R17*31 -> 3430.4841 | W17: 13 | X17: =X$5*W17 -> 1129.44 | Y17: =X17*Y$3 -> 113.79108 | Z17: =Y17*28 -> 3186.1502 | AA17: =Y17*30 -> 3413.7324 | AB17: =Y17*31 -> 3527.5235 | AD17: 13 | AE17: =AE$5*AD17 -> 1165.06 | AF17: =AE17*AF$3 -> 117.3798 | AG17: =AF17*28 -> 3286.6343 | AH17: =AF17*30 -> 3521.3938 | AI17: =AF17*31 -> 3638.7736 | AK17: 13 | AL17: =AL$5*AK17 -> 1250.86 | AM17: =AL17*AM$3 -> 126.02415 | AN17: =AM17*28 -> 3528.6761 | AO17: =AM17*30 -> 3780.7243 | AP17: =AM17*31 -> 3906.7485 | AR17: 13 | AS17: =AS$5*AR17 -> 1348.62 | AT17: =AS17*AT$3 -> 150.58691 | AU17: =AT17*28 -> 4216.4335 | AV17: =AT17*30 -> 4517.6073 | AW17: =AT17*31 -> 4668.1942 | AY17: 13 | AZ17: =AZ$5*AY17 -> 0 | BA17: =AZ17*BA$3 -> 0 | BB17: =BA17*28 -> 0 | BC17: =BA17*30 -> 0 | BD17: =BA17*31 -> 0 | BF17: 13 | BG17: =BG$5*BF17 -> 0 | BH17: =BG17*BH$3 -> 0 | BI17: =BH17*28 -> 0 | BJ17: =BH17*30 -> 0 | BK17: =BH17*31 -> 0 | BM17: 13 | BN17: =BN$5*BM17 -> 0 | BO17: =BN17*BO$3 -> 0 | BP17: =BO17*28 -> 0 | BQ17: =BO17*30 -> 0 | BR17: =BO17*31 -> 0 | BT17: 13 | BU17: =BU$5*BT17 -> 0 | BV17: =BU17*BV$3 -> 0 | BW17: =BV17*28 -> 0 | BX17: =BV17*30 -> 0 | BY17: =BV17*31 -> 0 | CA17: 13 | CB17: =CB$5*CA17 -> 0 | CC17: =CB17*CC$3 -> 0 | CD17: =CC17*28 -> 0 | CE17: =CC17*30 -> 0 | CF17: =CC17*31 -> 0 | CH17: 13 | CI17: =CI$5*CH17 -> 0 | CJ17: =CI17*CJ$3 -> 0 | CK17: =CJ17*28 -> 0 | CL17: =CJ17*30 -> 0 | CM17: =CJ17*31 -> 0 | CO17: 13 | CP17: =CP$5*CO17 -> 0 | CQ17: =CP17*CQ$3 -> 0 | CR17: =CQ17*28 -> 0 | CS17: =CQ17*30 -> 0 | CT17: =CQ17*31 -> 0 | CV17: 13 | CW17: =CW$5*CV17 -> 0 | CX17: =CW17*CX$3 -> 0 | CY17: =CX17*28 -> 0 | CZ17: =CX17*30 -> 0 | DA17: =CX17*31 -> 0 | DC17: 13 | DD17: =DD$5*DC17 -> 0 | DE17: =DD17*DE$3 -> 0 | DF17: =DE17*28 -> 0 | DG17: =DE17*30 -> 0 | DH17: =DE17*31 -> 0 | DJ17: 13 | DK17: =DK$5*DJ17 -> 0 | DL17: =DK17*DL$3 -> 0 | DM17: =DL17*28 -> 0 | DN17: =DL17*30 -> 0 | DO17: =DL17*31 -> 0 | DQ17: 13 | DR17: =DR$5*DQ17 -> 0 | DS17: =DR17*DS$3 -> 0 | DT17: =DS17*28 -> 0 | DU17: =DS17*30 -> 0 | DV17: =DS17*31 -> 0 | DX17: 13 | DY17: =DY$5*DX17 -> 0 | DZ17: =DY17*DZ$3 -> 0 | EA17: =DZ17*28 -> 0 | EB17: =DZ17*30 -> 0 | EC17: =DZ17*31 -> 0
B18: 14 | C18: =C$5*B18 -> 1056.86 | D18: =C18*D$3 -> 106.47865 | E18: =D18*28 -> 2981.4021 | F18: =D18*30 -> 3194.3594 | G18: =D18*31 -> 3300.838 | I18: 14 | J18: =J$5*I18 -> 1128.4 | K18: =J18*K$3 -> 113.6863 | L18: =K18*28 -> 3183.2164 | M18: =K18*30 -> 3410.589 | N18: =K18*31 -> 3524.2753 | P18: 14 | Q18: =Q$5*P18 -> 1182.86 | R18: =Q18*R$3 -> 119.17314 | S18: =R18*28 -> 3336.8481 | T18: =R18*30 -> 3575.1943 | U18: =R18*31 -> 3694.3675 | W18: 14 | X18: =X$5*W18 -> 1216.32 | Y18: =X18*Y$3 -> 122.54424 | Z18: =Y18*28 -> 3431.2387 | AA18: =Y18*30 -> 3676.3272 | AB18: =Y18*31 -> 3798.8714 | AD18: 14 | AE18: =AE$5*AD18 -> 1254.68 | AF18: =AE18*AF$3 -> 126.40901 | AG18: =AF18*28 -> 3539.4523 | AH18: =AF18*30 -> 3792.2703 | AI18: =AF18*31 -> 3918.6793 | AK18: 14 | AL18: =AL$5*AK18 -> 1347.08 | AM18: =AL18*AM$3 -> 135.71831 | AN18: =AM18*28 -> 3800.1127 | AO18: =AM18*30 -> 4071.5493 | AP18: =AM18*31 -> 4207.2676 | AR18: 14 | AS18: =AS$5*AR18 -> 1452.36 | AT18: =AS18*AT$3 -> 162.17052 | AU18: =AT18*28 -> 4540.7745 | AV18: =AT18*30 -> 4865.1155 | AW18: =AT18*31 -> 5027.286 | AY18: 14 | AZ18: =AZ$5*AY18 -> 0 | BA18: =AZ18*BA$3 -> 0 | BB18: =BA18*28 -> 0 | BC18: =BA18*30 -> 0 | BD18: =BA18*31 -> 0 | BF18: 14 | BG18: =BG$5*BF18 -> 0 | BH18: =BG18*BH$3 -> 0 | BI18: =BH18*28 -> 0 | BJ18: =BH18*30 -> 0 | BK18: =BH18*31 -> 0 | BM18: 14 | BN18: =BN$5*BM18 -> 0 | BO18: =BN18*BO$3 -> 0 | BP18: =BO18*28 -> 0 | BQ18: =BO18*30 -> 0 | BR18: =BO18*31 -> 0 | BT18: 14 | BU18: =BU$5*BT18 -> 0 | BV18: =BU18*BV$3 -> 0 | BW18: =BV18*28 -> 0 | BX18: =BV18*30 -> 0 | BY18: =BV18*31 -> 0 | CA18: 14 | CB18: =CB$5*CA18 -> 0 | CC18: =CB18*CC$3 -> 0 | CD18: =CC18*28 -> 0 | CE18: =CC18*30 -> 0 | CF18: =CC18*31 -> 0 | CH18: 14 | CI18: =CI$5*CH18 -> 0 | CJ18: =CI18*CJ$3 -> 0 | CK18: =CJ18*28 -> 0 | CL18: =CJ18*30 -> 0 | CM18: =CJ18*31 -> 0 | CO18: 14 | CP18: =CP$5*CO18 -> 0 | CQ18: =CP18*CQ$3 -> 0 | CR18: =CQ18*28 -> 0 | CS18: =CQ18*30 -> 0 | CT18: =CQ18*31 -> 0 | CV18: 14 | CW18: =CW$5*CV18 -> 0 | CX18: =CW18*CX$3 -> 0 | CY18: =CX18*28 -> 0 | CZ18: =CX18*30 -> 0 | DA18: =CX18*31 -> 0 | DC18: 14 | DD18: =DD$5*DC18 -> 0 | DE18: =DD18*DE$3 -> 0 | DF18: =DE18*28 -> 0 | DG18: =DE18*30 -> 0 | DH18: =DE18*31 -> 0 | DJ18: 14 | DK18: =DK$5*DJ18 -> 0 | DL18: =DK18*DL$3 -> 0 | DM18: =DL18*28 -> 0 | DN18: =DL18*30 -> 0 | DO18: =DL18*31 -> 0 | DQ18: 14 | DR18: =DR$5*DQ18 -> 0 | DS18: =DR18*DS$3 -> 0 | DT18: =DS18*28 -> 0 | DU18: =DS18*30 -> 0 | DV18: =DS18*31 -> 0 | DX18: 14 | DY18: =DY$5*DX18 -> 0 | DZ18: =DY18*DZ$3 -> 0 | EA18: =DZ18*28 -> 0 | EB18: =DZ18*30 -> 0 | EC18: =DZ18*31 -> 0
... B29: 25 | C29: =C$5*B29 -> 1887.25 | D29: =C29*D$3 -> 190.14044 | E29: =D29*28 -> 5323.9322 | F29: =D29*30 -> 5704.2131 | G29: =D29*31 -> 5894.3536 | I29: 25 | J29: =J$5*I29 -> 2015 | K29: =J29*K$3 -> 203.01125 | L29: =K29*28 -> 5684.315 | M29: =K29*30 -> 6090.3375 | N29: =K29*31 -> 6293.3488 | P29: 25 | Q29: =Q$5*P29 -> 2112.25 | R29: =Q29*R$3 -> 212.80919 | S29: =R29*28 -> 5958.6573 | T29: =R29*30 -> 6384.2756 | U29: =R29*31 -> 6597.0848 | W29: 25 | X29: =X$5*W29 -> 2172 | Y29: =X29*Y$3 -> 218.829 | Z29: =Y29*28 -> 6127.212 | AA29: =Y29*30 -> 6564.87 | AB29: =Y29*31 -> 6783.699 | AD29: 25 | AE29: =AE$5*AD29 -> 2240.5 | AF29: =AE29*AF$3 -> 225.73038 | AG29: =AF29*28 -> 6320.4505 | AH29: =AF29*30 -> 6771.9113 | AI29: =AF29*31 -> 6997.6416 | AK29: 25 | AL29: =AL$5*AK29 -> 2405.5 | AM29: =AL29*AM$3 -> 242.35413 | AN29: =AM29*28 -> 6785.9155 | AO29: =AM29*30 -> 7270.6238 | AP29: =AM29*31 -> 7512.9779 | AR29: 25 | AS29: =AS$5*AR29 -> 2593.5 | AT29: =AS29*AT$3 -> 289.59021 | AU29: =AT29*28 -> 8108.5259 | AV29: =AT29*30 -> 8687.7063 | AW29: =AT29*31 -> 8977.2965 | AY29: 25 | AZ29: =AZ$5*AY29 -> 0 | BA29: =AZ29*BA$3 -> 0 | BB29: =BA29*28 -> 0 | BC29: =BA29*30 -> 0 | BD29: =BA29*31 -> 0 | BF29: 25 | BG29: =BG$5*BF29 -> 0 | BH29: =BG29*BH$3 -> 0 | BI29: =BH29*28 -> 0 | BJ29: =BH29*30 -> 0 | BK29: =BH29*31 -> 0 | BM29: 25 | BN29: =BN$5*BM29 -> 0 | BO29: =BN29*BO$3 -> 0 | BP29: =BO29*28 -> 0 | BQ29: =BO29*30 -> 0 | BR29: =BO29*31 -> 0 | BT29: 25 | BU29: =BU$5*BT29 -> 0 | BV29: =BU29*BV$3 -> 0 | BW29: =BV29*28 -> 0 | BX29: =BV29*30 -> 0 | BY29: =BV29*31 -> 0 | CA29: 25 | CB29: =CB$5*CA29 -> 0 | CC29: =CB29*CC$3 -> 0 | CD29: =CC29*28 -> 0 | CE29: =CC29*30 -> 0 | CF29: =CC29*31 -> 0 | CH29: 25 | CI29: =CI$5*CH29 -> 0 | CJ29: =CI29*CJ$3 -> 0 | CK29: =CJ29*28 -> 0 | CL29: =CJ29*30 -> 0 | CM29: =CJ29*31 -> 0 | CO29: 25 | CP29: =CP$5*CO29 -> 0 | CQ29: =CP29*CQ$3 -> 0 | CR29: =CQ29*28 -> 0 | CS29: =CQ29*30 -> 0 | CT29: =CQ29*31 -> 0 | CV29: 25 | CW29: =CW$5*CV29 -> 0 | CX29: =CW29*CX$3 -> 0 | CY29: =CX29*28 -> 0 | CZ29: =CX29*30 -> 0 | DA29: =CX29*31 -> 0 | DC29: 25 | DD29: =DD$5*DC29 -> 0 | DE29: =DD29*DE$3 -> 0 | DF29: =DE29*28 -> 0 | DG29: =DE29*30 -> 0 | DH29: =DE29*31 -> 0 | DJ29: 25 | DK29: =DK$5*DJ29 -> 0 | DL29: =DK29*DL$3 -> 0 | DM29: =DL29*28 -> 0 | DN29: =DL29*30 -> 0 | DO29: =DL29*31 -> 0 | DQ29: 25 | DR29: =DR$5*DQ29 -> 0 | DS29: =DR29*DS$3 -> 0 | DT29: =DS29*28 -> 0 | DU29: =DS29*30 -> 0 | DV29: =DS29*31 -> 0 | DX29: 25 | DY29: =DY$5*DX29 -> 0 | DZ29: =DY29*DZ$3 -> 0 | EA29: =DZ29*28 -> 0 | EB29: =DZ29*30 -> 0 | EC29: =DZ29*31 -> 0

Sheet TblISR
A1: Total de pensión mensual | B1: ='Cálculo de Pensión'!F93 -> 0 | F1: Tablas ISR 2023 pagos mensuales
A2: Excensión (15 UMAs) | B2: ='Cálculo de Pensión'!F94 -> 47305.44 | F2: Tarifa del Impuesto Sobre la Renta
A3: BASE GRAVABLE | B3: =IF(B1-B2<0,0,B1-B2) -> 0 | F3: Límite inferior | G3: Límite superior | H3: Cuota fija | I3: % Sobre excedente
A4: LIMITE INFERIOR | B4: =LOOKUP(B3,$F$5:$G$15,$F$5:$F$15) -> 0 | I4: del límite inferior
A5: DIFERENCIA LIMITE INFERIOR | B5: =+B3-B4 -> 0 | F5: 0 | G5: 746.04 | H5: 0 | I5: 0.0192
A6: PORCENTAJE LIMITE INFERIOR | B6: =LOOKUP(B3,F5:G15,I5:I15) -> 0.0192 | F6: 746.05 | G6: 6332.05 | H6: 14.32 | I6: 0.064
A7: IMPUESTO MARGINAL | B7: =+B5*B6 -> 0 | F7: =G6+0.01 -> 6332.06 | G7: 11128.01 | H7: 371.83 | I7: 0.1088
A8: CUOTA FIJA | B8: =LOOKUP(B3,$F$5:$G$15,H5:H15) -> 0 | F8: =G7+0.01 -> 11128.02 | G8: 12935.82 | H8: 893.63 | I8: 0.16
A9: IMPUESTO A PAGAR | B9: =+B7+B8 -> 0 | F9: =G8+0.01 -> 12935.83 | G9: 15487.71 | H9: 1182.88 | I9: 0.1792
F10: =G9+0.01 -> 15487.72 | G10: 31236.49 | H10: 1640.18 | I10: 0.2136
F11: =G10+0.01 -> 31236.5 | G11: 49233 | H11: 5004.12 | I11: 0.2352
F12: =G11+0.01 -> 49233.01 | G12: 93993.9 | H12: 9236.89 | I12: 0.3
F13: =G12+0.01 -> 93993.91 | G13: 125325.2 | H13: 22665.17 | I13: 0.32
F14: =G13+0.01 -> 125325.21 | G14: 375975.61 | H14: 32691.18 | I14: 0.34
F15: =G14+0.01 -> 375975.62 | G15: En adelante | H15: 117912.32 | I15: 0.35

Sheet TblPorcentajesLey73
B4: Salario en Veces UMA | J4: Pensión Mínima Garantizada
B5: De | C5: a | D5: Cuantía Básica | E5: Incremento Anual | G5: Edad de Retiro | H5: Incremento anual | J5: Año | K5: S.M. | L5: Pensión Mínima
B6: 0 | C6: 1 | D6: 0.8 | E6: 0.00563 | G6: 60 | H6: 0.75 | J6: 2017 | K6: 80.04 | L6: =K6*365/12*1.11 -> 2702.3505 | N6: Total semanas cotizadas: | O6: ='Cálculo de Pensión'!$F$16 -> 819 | R6: 0 | S6: 0
B7: 1.01 | C7: 1.25 | D7: 0.8 | E7: 0.00563 | G7: 61 | H7: 0.8 | J7: 2018 | K7: 88.36 | L7: =K7*365/12*1.11 -> 2983.2545 | N7: Semanas mínimas requeridas: | O7: 500 | R7: 13 | S7: 0.5
B8: 1.26 | C8: 1.5 | D8: 0.7711 | E8: 0.00814 | G8: 62 | H8: 0.85 | J8: 2019 | K8: 102.68 | L8: =K8*365/12*1.11 -> 3466.7335 | N8: Excedente: | O8: =O6-O7 -> 319 | R8: 26.1 | S8: 1
B9: 1.51 | C9: 1.75 | D9: 0.5518 | E9: 0.01178 | G9: 63 | H9: 0.9 | J9: 2020 | K9: 123.22 | L9: =K9*365/12*1.11 -> 4160.2153 | O9: 52
B10: 1.76 | C10: 2 | D10: 0.4923 | E10: 0.0143 | G10: 64 | H10: 0.95 | J10: 2021 | K10: 141.7 | L10: =K10*365/12*1.11 -> 4784.1462 | O10: =TRUNC(O8/O9) -> 6
B11: 2.01 | C11: 2.25 | D11: 0.4267 | E11: 0.01615 | G11: 65 | H11: 1 | J11: 2022 | K11: 172.87 | L11: =K11*365/12*1.11 -> 5836.5234 | O11: 52
B12: 2.26 | C12: 2.5 | D12: 0.3765 | E12: 0.01756 | J12: 2023 | K12: 207.44 | L12: =K12*365/12*1.11 -> 7003.693 | O12: =O10*O11 -> 312
B13: 2.51 | C13: 2.75 | D13: 0.3368 | E13: 0.01868
B14: 2.76 | C14: 3 | D14: 0.3048 | E14: 0.01958 | O14: =O8 -> 319
B15: 3.01 | C15: 3.25 | D15: 0.2783 | E15: 0.02033 | O15: =O12 -> 312
B16: 3.26 | C16: 3.5 | D16: 0.256 | E16: 0.02096 | O16: =O14-O15 -> 7
B17: 3.51 | C17: 3.75 | D17: 0.237 | E17: 0.02149 | O17: =VLOOKUP(O16,$R$6:$S$8,2) -> 0
B18: 3.76 | C18: 4 | D18: 0.2207 | E18: 0.02195
B19: 4.01 | C19: 4.25 | D19: 0.2065 | E19: 0.02235 | O19: =O10 -> 6
B20: 4.26 | C20: 4.5 | D20: 0.1939 | E20: 0.02271 | O20: =O17 -> 0
B21: 4.51 | C21: 4.75 | D21: 0.1829 | E21: 0.02302 | O21: =SUM(O19:O20) -> 6
B22: 4.76 | C22: 5 | D22: 0.173 | E22: 0.0233
B23: 5.01 | C23: 5.25 | D23: 0.1641 | E23: 0.02355
B24: 5.26 | C24: 5.5 | D24: 0.1561 | E24: 0.02377
B25: 5.51 | C25: 5.75 | D25: 0.1488 | E25: 0.02398
B26: 5.76 | C26: 6 | D26: 0.1422 | E26: 0.02416
B27: 6.01 | C27: 6.01 | D27: 0.1362 | E27: 0.02433
B28: 6.02 | C28: 99999999 | D28: 0.13 | E28: 0.0245
M34: =26250*2 -> 52500
